{
  "filename": "라쿠.png",
  "text": "영 수 증 \n기린 귀하 \n2024-10-07 (월) \n라쿠(Raku) \n부르뎅 1층 49호 \n02-2231-6263 \n010-9778-4302 \n2024-10-07 00 : 00 (월) 62, 100 청구 \n품명 단가 수량 금액 \nx후드/곤/13 21,000 1 21, 000 \n브루노P/메/13 20,000 1 20, 000 \n컬쳐set/먹/19 28, 000 1 28, 000 \n판매소계 3건 3 69, 000 \n전 잔 액: 0 \n당일합계: 69 , 000 \n할인금액 : 6, 900 \n당 잔: 62,100 \n신한은행 110-397-801014 라쿠 입금은 상호명으로~~",
  "confidence": 0.9913,
  "words": [
    {
      "boundingBox": {
        "vertices": [
          {
            "x": 249,
            "y": 55
          },
          {
            "x": 282,
            "y": 55
          },
          {
            "x": 283,
            "y": 93
          },
          {
            "x": 249,
            "y": 93
          }
        ]
      },
      "confidence": 0.9867,
      "id": 0,
      "text": "영"
    },
    {
      "boundingBox": {
        "vertices": [
          {
            "x": 314,
            "y": 55
          },
          {
            "x": 350,
            "y": 55
          },
          {
            "x": 350,
            "y": 95
          },
          {
            "x": 314,
            "y": 95
          }
        ]
      },
      "confidence": 0.9974,
      "id": 1,
      "text": "수"
    },
    {
      "boundingBox": {
        "vertices": [
          {
            "x": 378,
            "y": 55
          },
          {
            "x": 413,
            "y": 55
          },
          {
            "x": 414,
            "y": 94
          },
          {
            "x": 379,
            "y": 94
          }
        ]
      },
      "confidence": 0.9951,
      "id": 2,
      "text": "증"
    },
    {
      "boundingBox": {
        "vertices": [
          {
            "x": 513,
            "y": 106
          },
          {
            "x": 576,
            "y": 106
          },
          {
            "x": 576,
            "y": 140
          },
          {
            "x": 513,
            "y": 140
          }
        ]
      },
      "confidence": 0.9978,
      "id": 3,
      "text": "기린"
    },
    {
      "boundingBox": {
        "vertices": [
          {
            "x": 600,
            "y": 109
          },
          {
            "x": 657,
            "y": 109
          },
          {
            "x": 657,
            "y": 140
          },
          {
            "x": 600,
            "y": 140
          }
        ]
      },
      "confidence": 0.9963,
      "id": 4,
      "text": "귀하"
    },
    {
      "boundingBox": {
        "vertices": [
          {
            "x": 428,
            "y": 148
          },
          {
            "x": 587,
            "y": 148
          },
          {
            "x": 587,
            "y": 172
          },
          {
            "x": 428,
            "y": 172
          }
        ]
      },
      "confidence": 0.9987,
      "id": 5,
      "text": "2024-10-07"
    },
    {
      "boundingBox": {
        "vertices": [
          {
            "x": 603,
            "y": 149
          },
          {
            "x": 656,
            "y": 148
          },
          {
            "x": 657,
            "y": 176
          },
          {
            "x": 604,
            "y": 176
          }
        ]
      },
      "confidence": 0.9969,
      "id": 6,
      "text": "(월)"
    },
    {
      "boundingBox": {
        "vertices": [
          {
            "x": 233,
            "y": 215
          },
          {
            "x": 429,
            "y": 215
          },
          {
            "x": 429,
            "y": 252
          },
          {
            "x": 233,
            "y": 252
          }
        ]
      },
      "confidence": 0.9989,
      "id": 7,
      "text": "라쿠(Raku)"
    },
    {
      "boundingBox": {
        "vertices": [
          {
            "x": 235,
            "y": 258
          },
          {
            "x": 302,
            "y": 258
          },
          {
            "x": 302,
            "y": 282
          },
          {
            "x": 235,
            "y": 282
          }
        ]
      },
      "confidence": 0.9907,
      "id": 8,
      "text": "부르뎅"
    },
    {
      "boundingBox": {
        "vertices": [
          {
            "x": 319,
            "y": 258
          },
          {
            "x": 358,
            "y": 258
          },
          {
            "x": 358,
            "y": 282
          },
          {
            "x": 319,
            "y": 282
          }
        ]
      },
      "confidence": 0.9959,
      "id": 9,
      "text": "1층"
    },
    {
      "boundingBox": {
        "vertices": [
          {
            "x": 372,
            "y": 258
          },
          {
            "x": 428,
            "y": 257
          },
          {
            "x": 428,
            "y": 280
          },
          {
            "x": 373,
            "y": 281
          }
        ]
      },
      "confidence": 0.9971,
      "id": 10,
      "text": "49호"
    },
    {
      "boundingBox": {
        "vertices": [
          {
            "x": 236,
            "y": 289
          },
          {
            "x": 426,
            "y": 289
          },
          {
            "x": 426,
            "y": 311
          },
          {
            "x": 236,
            "y": 311
          }
        ]
      },
      "confidence": 0.9976,
      "id": 11,
      "text": "02-2231-6263"
    },
    {
      "boundingBox": {
        "vertices": [
          {
            "x": 228,
            "y": 320
          },
          {
            "x": 434,
            "y": 320
          },
          {
            "x": 434,
            "y": 344
          },
          {
            "x": 228,
            "y": 344
          }
        ]
      },
      "confidence": 0.9988,
      "id": 12,
      "text": "010-9778-4302"
    },
    {
      "boundingBox": {
        "vertices": [
          {
            "x": 6,
            "y": 384
          },
          {
            "x": 164,
            "y": 384
          },
          {
            "x": 164,
            "y": 408
          },
          {
            "x": 6,
            "y": 407
          }
        ]
      },
      "confidence": 0.9986,
      "id": 13,
      "text": "2024-10-07"
    },
    {
      "boundingBox": {
        "vertices": [
          {
            "x": 179,
            "y": 384
          },
          {
            "x": 212,
            "y": 384
          },
          {
            "x": 212,
            "y": 408
          },
          {
            "x": 179,
            "y": 408
          }
        ]
      },
      "confidence": 0.986,
      "id": 14,
      "text": "00"
    },
    {
      "boundingBox": {
        "vertices": [
          {
            "x": 215,
            "y": 389
          },
          {
            "x": 223,
            "y": 389
          },
          {
            "x": 223,
            "y": 406
          },
          {
            "x": 215,
            "y": 406
          }
        ]
      },
      "confidence": 0.9967,
      "id": 15,
      "text": ":"
    },
    {
      "boundingBox": {
        "vertices": [
          {
            "x": 227,
            "y": 384
          },
          {
            "x": 260,
            "y": 384
          },
          {
            "x": 260,
            "y": 408
          },
          {
            "x": 227,
            "y": 408
          }
        ]
      },
      "confidence": 0.9851,
      "id": 16,
      "text": "00"
    },
    {
      "boundingBox": {
        "vertices": [
          {
            "x": 276,
            "y": 383
          },
          {
            "x": 329,
            "y": 383
          },
          {
            "x": 329,
            "y": 411
          },
          {
            "x": 276,
            "y": 411
          }
        ]
      },
      "confidence": 0.9972,
      "id": 17,
      "text": "(월)"
    },
    {
      "boundingBox": {
        "vertices": [
          {
            "x": 451,
            "y": 382
          },
          {
            "x": 495,
            "y": 386
          },
          {
            "x": 493,
            "y": 412
          },
          {
            "x": 449,
            "y": 408
          }
        ]
      },
      "confidence": 0.9973,
      "id": 18,
      "text": "62,"
    },
    {
      "boundingBox": {
        "vertices": [
          {
            "x": 498,
            "y": 385
          },
          {
            "x": 545,
            "y": 383
          },
          {
            "x": 546,
            "y": 408
          },
          {
            "x": 498,
            "y": 409
          }
        ]
      },
      "confidence": 0.9976,
      "id": 19,
      "text": "100"
    },
    {
      "boundingBox": {
        "vertices": [
          {
            "x": 612,
            "y": 383
          },
          {
            "x": 657,
            "y": 384
          },
          {
            "x": 657,
            "y": 409
          },
          {
            "x": 611,
            "y": 408
          }
        ]
      },
      "confidence": 0.9992,
      "id": 20,
      "text": "청구"
    },
    {
      "boundingBox": {
        "vertices": [
          {
            "x": 0,
            "y": 454
          },
          {
            "x": 43,
            "y": 454
          },
          {
            "x": 43,
            "y": 478
          },
          {
            "x": 0,
            "y": 478
          }
        ]
      },
      "confidence": 0.9939,
      "id": 21,
      "text": "품명"
    },
    {
      "boundingBox": {
        "vertices": [
          {
            "x": 452,
            "y": 454
          },
          {
            "x": 498,
            "y": 454
          },
          {
            "x": 498,
            "y": 478
          },
          {
            "x": 452,
            "y": 478
          }
        ]
      },
      "confidence": 0.9981,
      "id": 22,
      "text": "단가"
    },
    {
      "boundingBox": {
        "vertices": [
          {
            "x": 525,
            "y": 454
          },
          {
            "x": 571,
            "y": 453
          },
          {
            "x": 572,
            "y": 478
          },
          {
            "x": 526,
            "y": 479
          }
        ]
      },
      "confidence": 0.9971,
      "id": 23,
      "text": "수량"
    },
    {
      "boundingBox": {
        "vertices": [
          {
            "x": 618,
            "y": 454
          },
          {
            "x": 663,
            "y": 454
          },
          {
            "x": 663,
            "y": 478
          },
          {
            "x": 618,
            "y": 478
          }
        ]
      },
      "confidence": 0.9975,
      "id": 24,
      "text": "금액"
    },
    {
      "boundingBox": {
        "vertices": [
          {
            "x": 0,
            "y": 543
          },
          {
            "x": 146,
            "y": 543
          },
          {
            "x": 146,
            "y": 568
          },
          {
            "x": 0,
            "y": 568
          }
        ]
      },
      "confidence": 0.9863,
      "id": 25,
      "text": "x후드/곤/13"
    },
    {
      "boundingBox": {
        "vertices": [
          {
            "x": 358,
            "y": 544
          },
          {
            "x": 454,
            "y": 543
          },
          {
            "x": 454,
            "y": 570
          },
          {
            "x": 359,
            "y": 571
          }
        ]
      },
      "confidence": 0.9981,
      "id": 26,
      "text": "21,000"
    },
    {
      "boundingBox": {
        "vertices": [
          {
            "x": 492,
            "y": 545
          },
          {
            "x": 508,
            "y": 545
          },
          {
            "x": 508,
            "y": 566
          },
          {
            "x": 493,
            "y": 566
          }
        ]
      },
      "confidence": 0.9945,
      "id": 27,
      "text": "1"
    },
    {
      "boundingBox": {
        "vertices": [
          {
            "x": 568,
            "y": 543
          },
          {
            "x": 615,
            "y": 545
          },
          {
            "x": 614,
            "y": 571
          },
          {
            "x": 567,
            "y": 569
          }
        ]
      },
      "confidence": 0.9984,
      "id": 28,
      "text": "21,"
    },
    {
      "boundingBox": {
        "vertices": [
          {
            "x": 615,
            "y": 544
          },
          {
            "x": 664,
            "y": 543
          },
          {
            "x": 664,
            "y": 568
          },
          {
            "x": 616,
            "y": 569
          }
        ]
      },
      "confidence": 0.9904,
      "id": 29,
      "text": "000"
    },
    {
      "boundingBox": {
        "vertices": [
          {
            "x": 0,
            "y": 588
          },
          {
            "x": 169,
            "y": 588
          },
          {
            "x": 169,
            "y": 613
          },
          {
            "x": 0,
            "y": 613
          }
        ]
      },
      "confidence": 0.9962,
      "id": 30,
      "text": "브루노P/메/13"
    },
    {
      "boundingBox": {
        "vertices": [
          {
            "x": 358,
            "y": 589
          },
          {
            "x": 454,
            "y": 588
          },
          {
            "x": 454,
            "y": 616
          },
          {
            "x": 359,
            "y": 617
          }
        ]
      },
      "confidence": 0.9981,
      "id": 31,
      "text": "20,000"
    },
    {
      "boundingBox": {
        "vertices": [
          {
            "x": 492,
            "y": 590
          },
          {
            "x": 508,
            "y": 590
          },
          {
            "x": 508,
            "y": 611
          },
          {
            "x": 493,
            "y": 612
          }
        ]
      },
      "confidence": 0.9952,
      "id": 32,
      "text": "1"
    },
    {
      "boundingBox": {
        "vertices": [
          {
            "x": 569,
            "y": 587
          },
          {
            "x": 615,
            "y": 591
          },
          {
            "x": 612,
            "y": 617
          },
          {
            "x": 567,
            "y": 613
          }
        ]
      },
      "confidence": 0.9964,
      "id": 33,
      "text": "20,"
    },
    {
      "boundingBox": {
        "vertices": [
          {
            "x": 616,
            "y": 589
          },
          {
            "x": 664,
            "y": 588
          },
          {
            "x": 664,
            "y": 613
          },
          {
            "x": 616,
            "y": 614
          }
        ]
      },
      "confidence": 0.9904,
      "id": 34,
      "text": "000"
    },
    {
      "boundingBox": {
        "vertices": [
          {
            "x": 1,
            "y": 633
          },
          {
            "x": 178,
            "y": 633
          },
          {
            "x": 178,
            "y": 659
          },
          {
            "x": 1,
            "y": 659
          }
        ]
      },
      "confidence": 0.9948,
      "id": 35,
      "text": "컬쳐set/먹/19"
    },
    {
      "boundingBox": {
        "vertices": [
          {
            "x": 360,
            "y": 632
          },
          {
            "x": 404,
            "y": 636
          },
          {
            "x": 401,
            "y": 662
          },
          {
            "x": 357,
            "y": 658
          }
        ]
      },
      "confidence": 0.9982,
      "id": 36,
      "text": "28,"
    },
    {
      "boundingBox": {
        "vertices": [
          {
            "x": 406,
            "y": 633
          },
          {
            "x": 454,
            "y": 633
          },
          {
            "x": 454,
            "y": 658
          },
          {
            "x": 406,
            "y": 658
          }
        ]
      },
      "confidence": 0.9902,
      "id": 37,
      "text": "000"
    },
    {
      "boundingBox": {
        "vertices": [
          {
            "x": 492,
            "y": 635
          },
          {
            "x": 508,
            "y": 635
          },
          {
            "x": 508,
            "y": 656
          },
          {
            "x": 493,
            "y": 657
          }
        ]
      },
      "confidence": 0.9945,
      "id": 38,
      "text": "1"
    },
    {
      "boundingBox": {
        "vertices": [
          {
            "x": 569,
            "y": 632
          },
          {
            "x": 614,
            "y": 636
          },
          {
            "x": 611,
            "y": 662
          },
          {
            "x": 567,
            "y": 658
          }
        ]
      },
      "confidence": 0.9978,
      "id": 39,
      "text": "28,"
    },
    {
      "boundingBox": {
        "vertices": [
          {
            "x": 616,
            "y": 633
          },
          {
            "x": 664,
            "y": 633
          },
          {
            "x": 664,
            "y": 659
          },
          {
            "x": 616,
            "y": 659
          }
        ]
      },
      "confidence": 0.9904,
      "id": 40,
      "text": "000"
    },
    {
      "boundingBox": {
        "vertices": [
          {
            "x": 123,
            "y": 671
          },
          {
            "x": 214,
            "y": 671
          },
          {
            "x": 214,
            "y": 696
          },
          {
            "x": 123,
            "y": 696
          }
        ]
      },
      "confidence": 0.9969,
      "id": 41,
      "text": "판매소계"
    },
    {
      "boundingBox": {
        "vertices": [
          {
            "x": 383,
            "y": 672
          },
          {
            "x": 421,
            "y": 672
          },
          {
            "x": 421,
            "y": 696
          },
          {
            "x": 383,
            "y": 696
          }
        ]
      },
      "confidence": 0.9966,
      "id": 42,
      "text": "3건"
    },
    {
      "boundingBox": {
        "vertices": [
          {
            "x": 456,
            "y": 672
          },
          {
            "x": 472,
            "y": 672
          },
          {
            "x": 472,
            "y": 695
          },
          {
            "x": 456,
            "y": 695
          }
        ]
      },
      "confidence": 0.9967,
      "id": 43,
      "text": "3"
    },
    {
      "boundingBox": {
        "vertices": [
          {
            "x": 562,
            "y": 671
          },
          {
            "x": 607,
            "y": 673
          },
          {
            "x": 606,
            "y": 699
          },
          {
            "x": 561,
            "y": 697
          }
        ]
      },
      "confidence": 0.9983,
      "id": 44,
      "text": "69,"
    },
    {
      "boundingBox": {
        "vertices": [
          {
            "x": 610,
            "y": 672
          },
          {
            "x": 658,
            "y": 672
          },
          {
            "x": 658,
            "y": 697
          },
          {
            "x": 610,
            "y": 697
          }
        ]
      },
      "confidence": 0.9897,
      "id": 45,
      "text": "000"
    },
    {
      "boundingBox": {
        "vertices": [
          {
            "x": 76,
            "y": 735
          },
          {
            "x": 98,
            "y": 735
          },
          {
            "x": 98,
            "y": 759
          },
          {
            "x": 76,
            "y": 760
          }
        ]
      },
      "confidence": 0.9946,
      "id": 46,
      "text": "전"
    },
    {
      "boundingBox": {
        "vertices": [
          {
            "x": 114,
            "y": 735
          },
          {
            "x": 138,
            "y": 735
          },
          {
            "x": 138,
            "y": 759
          },
          {
            "x": 114,
            "y": 759
          }
        ]
      },
      "confidence": 0.9928,
      "id": 47,
      "text": "잔"
    },
    {
      "boundingBox": {
        "vertices": [
          {
            "x": 154,
            "y": 735
          },
          {
            "x": 188,
            "y": 735
          },
          {
            "x": 188,
            "y": 760
          },
          {
            "x": 154,
            "y": 760
          }
        ]
      },
      "confidence": 0.9869,
      "id": 48,
      "text": "액:"
    },
    {
      "boundingBox": {
        "vertices": [
          {
            "x": 641,
            "y": 736
          },
          {
            "x": 657,
            "y": 736
          },
          {
            "x": 657,
            "y": 758
          },
          {
            "x": 641,
            "y": 758
          }
        ]
      },
      "confidence": 0.9736,
      "id": 49,
      "text": "0"
    },
    {
      "boundingBox": {
        "vertices": [
          {
            "x": 85,
            "y": 766
          },
          {
            "x": 188,
            "y": 766
          },
          {
            "x": 188,
            "y": 791
          },
          {
            "x": 85,
            "y": 791
          }
        ]
      },
      "confidence": 0.9837,
      "id": 50,
      "text": "당일합계:"
    },
    {
      "boundingBox": {
        "vertices": [
          {
            "x": 561,
            "y": 767
          },
          {
            "x": 593,
            "y": 767
          },
          {
            "x": 593,
            "y": 791
          },
          {
            "x": 561,
            "y": 791
          }
        ]
      },
      "confidence": 0.9988,
      "id": 51,
      "text": "69"
    },
    {
      "boundingBox": {
        "vertices": [
          {
            "x": 597,
            "y": 770
          },
          {
            "x": 605,
            "y": 770
          },
          {
            "x": 605,
            "y": 793
          },
          {
            "x": 597,
            "y": 793
          }
        ]
      },
      "confidence": 0.9913,
      "id": 52,
      "text": ","
    },
    {
      "boundingBox": {
        "vertices": [
          {
            "x": 609,
            "y": 766
          },
          {
            "x": 658,
            "y": 766
          },
          {
            "x": 658,
            "y": 791
          },
          {
            "x": 609,
            "y": 791
          }
        ]
      },
      "confidence": 0.9893,
      "id": 53,
      "text": "000"
    },
    {
      "boundingBox": {
        "vertices": [
          {
            "x": 85,
            "y": 798
          },
          {
            "x": 188,
            "y": 798
          },
          {
            "x": 188,
            "y": 823
          },
          {
            "x": 85,
            "y": 823
          }
        ]
      },
      "confidence": 0.9952,
      "id": 54,
      "text": "할인금액 :"
    },
    {
      "boundingBox": {
        "vertices": [
          {
            "x": 577,
            "y": 799
          },
          {
            "x": 607,
            "y": 799
          },
          {
            "x": 608,
            "y": 825
          },
          {
            "x": 578,
            "y": 826
          }
        ]
      },
      "confidence": 0.9983,
      "id": 55,
      "text": "6,"
    },
    {
      "boundingBox": {
        "vertices": [
          {
            "x": 610,
            "y": 799
          },
          {
            "x": 658,
            "y": 799
          },
          {
            "x": 658,
            "y": 823
          },
          {
            "x": 610,
            "y": 823
          }
        ]
      },
      "confidence": 0.992,
      "id": 56,
      "text": "900"
    },
    {
      "boundingBox": {
        "vertices": [
          {
            "x": 115,
            "y": 831
          },
          {
            "x": 138,
            "y": 830
          },
          {
            "x": 138,
            "y": 855
          },
          {
            "x": 115,
            "y": 855
          }
        ]
      },
      "confidence": 0.9952,
      "id": 57,
      "text": "당"
    },
    {
      "boundingBox": {
        "vertices": [
          {
            "x": 152,
            "y": 830
          },
          {
            "x": 188,
            "y": 830
          },
          {
            "x": 188,
            "y": 855
          },
          {
            "x": 153,
            "y": 855
          }
        ]
      },
      "confidence": 0.7764,
      "id": 58,
      "text": "잔:"
    },
    {
      "boundingBox": {
        "vertices": [
          {
            "x": 561,
            "y": 831
          },
          {
            "x": 658,
            "y": 831
          },
          {
            "x": 658,
            "y": 857
          },
          {
            "x": 561,
            "y": 857
          }
        ]
      },
      "confidence": 0.9987,
      "id": 59,
      "text": "62,100"
    },
    {
      "boundingBox": {
        "vertices": [
          {
            "x": 6,
            "y": 893
          },
          {
            "x": 96,
            "y": 893
          },
          {
            "x": 96,
            "y": 919
          },
          {
            "x": 6,
            "y": 919
          }
        ]
      },
      "confidence": 0.9982,
      "id": 60,
      "text": "신한은행"
    },
    {
      "boundingBox": {
        "vertices": [
          {
            "x": 113,
            "y": 894
          },
          {
            "x": 335,
            "y": 894
          },
          {
            "x": 335,
            "y": 917
          },
          {
            "x": 113,
            "y": 917
          }
        ]
      },
      "confidence": 0.9986,
      "id": 61,
      "text": "110-397-801014"
    },
    {
      "boundingBox": {
        "vertices": [
          {
            "x": 351,
            "y": 893
          },
          {
            "x": 396,
            "y": 893
          },
          {
            "x": 396,
            "y": 919
          },
          {
            "x": 351,
            "y": 919
          }
        ]
      },
      "confidence": 0.996,
      "id": 62,
      "text": "라쿠"
    },
    {
      "boundingBox": {
        "vertices": [
          {
            "x": 413,
            "y": 893
          },
          {
            "x": 480,
            "y": 893
          },
          {
            "x": 480,
            "y": 919
          },
          {
            "x": 413,
            "y": 919
          }
        ]
      },
      "confidence": 0.9972,
      "id": 63,
      "text": "입금은"
    },
    {
      "boundingBox": {
        "vertices": [
          {
            "x": 496,
            "y": 893
          },
          {
            "x": 643,
            "y": 893
          },
          {
            "x": 643,
            "y": 918
          },
          {
            "x": 496,
            "y": 918
          }
        ]
      },
      "confidence": 0.9977,
      "id": 64,
      "text": "상호명으로~~"
    }
  ]
}
