{
  "text": "영 수 증(공급받는자) \n길라인(중도매12시내림) 귀히 \n-재발행 2024-10-06(일) 22:54:49 \n앤셜리(Anne shirley) \n페인트타운 3F 302.3호 \nHP :010-3103-3420 \nKakao story D \nanneshirlev0922 (사업자 확인후 가능) \ninstagram :anneshirley official \n\"판가는 도매가의 1.6배입니다 \n반드시 지켜주세요** \n본사의 도매거래 규칙위반시 법적대응합니다 \n(본부카스기재) 한음법무법인 \n24-10-07(월) 336,100 청구 \n품명 단가 수량 금액 \n래빗드레스/래빗/m \n29,000 1 29,000 \n마릴라슈트/도트(민트)/m \n24,000 1 24,000 \n벨르터들넥/소라/s \n8,000 1 8,000 \n벨르터들넥/소라/m \n8.000 1 8.000 \n※안나드레스/블랙/m \n23.000 2 46,000 \n※퓨어레이스원피스슈트/크림/s \n27,000 1 27,000 \n판매소계 6건 7 142.000 \n전 잔: 208,300 \n당일합계: 142,000 \n할인금액: 14200 \n당 잔: 336,100 \n매입전잔: 0 \n매입잔액: 0 \n※ 표시는 미송상품입니다. \n*입금은 반드시 상호명으로 입금해주세요 \n*세금계산서 100% 발행 \n*상기금액은 부가세 별도 금액입니다 \n*VAT별도, 세금계산서 매월말일마감 \n(전자마감 수정불가) \n계산서 관련문의 담당자 010-3103-3420 \n*교환 일주일이내 \n<니트 화이트색상,시즌지난상품> \n교환 및 환불 불가합니다 \n*매입금액은 2주이내 사용가능합니다 \n· 卸売規則事項です \n交換及び返品資料は、 いかなる場合でも お願いします \n本社 で負担いたしません \n24264654487996",
  "confidence": 0.958,
  "words": [
    {
      "boundingBox": {
        "vertices": [
          {
            "x": 103,
            "y": 1
          },
          {
            "x": 116,
            "y": 1
          },
          {
            "x": 116,
            "y": 15
          },
          {
            "x": 103,
            "y": 15
          }
        ]
      },
      "confidence": 0.9735,
      "id": 0,
      "text": "영"
    },
    {
      "boundingBox": {
        "vertices": [
          {
            "x": 121,
            "y": 2
          },
          {
            "x": 135,
            "y": 2
          },
          {
            "x": 135,
            "y": 15
          },
          {
            "x": 121,
            "y": 15
          }
        ]
      },
      "confidence": 0.9819,
      "id": 1,
      "text": "수"
    },
    {
      "boundingBox": {
        "vertices": [
          {
            "x": 140,
            "y": 2
          },
          {
            "x": 204,
            "y": 2
          },
          {
            "x": 204,
            "y": 15
          },
          {
            "x": 140,
            "y": 15
          }
        ]
      },
      "confidence": 0.986,
      "id": 2,
      "text": "증(공급받는자)"
    },
    {
      "boundingBox": {
        "vertices": [
          {
            "x": 170,
            "y": 17
          },
          {
            "x": 268,
            "y": 17
          },
          {
            "x": 268,
            "y": 27
          },
          {
            "x": 170,
            "y": 27
          }
        ]
      },
      "confidence": 0.8852,
      "id": 3,
      "text": "길라인(중도매12시내림)"
    },
    {
      "boundingBox": {
        "vertices": [
          {
            "x": 270,
            "y": 17
          },
          {
            "x": 287,
            "y": 17
          },
          {
            "x": 287,
            "y": 26
          },
          {
            "x": 270,
            "y": 26
          }
        ]
      },
      "confidence": 0.9728,
      "id": 4,
      "text": "귀히"
    },
    {
      "boundingBox": {
        "vertices": [
          {
            "x": 29,
            "y": 27
          },
          {
            "x": 59,
            "y": 27
          },
          {
            "x": 59,
            "y": 37
          },
          {
            "x": 29,
            "y": 37
          }
        ]
      },
      "confidence": 0.9798,
      "id": 5,
      "text": "-재발행"
    },
    {
      "boundingBox": {
        "vertices": [
          {
            "x": 181,
            "y": 27
          },
          {
            "x": 249,
            "y": 27
          },
          {
            "x": 249,
            "y": 37
          },
          {
            "x": 181,
            "y": 37
          }
        ]
      },
      "confidence": 0.9622,
      "id": 6,
      "text": "2024-10-06(일)"
    },
    {
      "boundingBox": {
        "vertices": [
          {
            "x": 250,
            "y": 27
          },
          {
            "x": 287,
            "y": 27
          },
          {
            "x": 287,
            "y": 37
          },
          {
            "x": 250,
            "y": 37
          }
        ]
      },
      "confidence": 0.997,
      "id": 7,
      "text": "22:54:49"
    },
    {
      "boundingBox": {
        "vertices": [
          {
            "x": 93,
            "y": 51
          },
          {
            "x": 165,
            "y": 51
          },
          {
            "x": 165,
            "y": 64
          },
          {
            "x": 93,
            "y": 64
          }
        ]
      },
      "confidence": 0.971,
      "id": 8,
      "text": "앤셜리(Anne"
    },
    {
      "boundingBox": {
        "vertices": [
          {
            "x": 167,
            "y": 51
          },
          {
            "x": 210,
            "y": 51
          },
          {
            "x": 210,
            "y": 64
          },
          {
            "x": 167,
            "y": 64
          }
        ]
      },
      "confidence": 0.9793,
      "id": 9,
      "text": "shirley)"
    },
    {
      "boundingBox": {
        "vertices": [
          {
            "x": 16,
            "y": 65
          },
          {
            "x": 59,
            "y": 65
          },
          {
            "x": 59,
            "y": 75
          },
          {
            "x": 16,
            "y": 75
          }
        ]
      },
      "confidence": 0.9945,
      "id": 10,
      "text": "페인트타운"
    },
    {
      "boundingBox": {
        "vertices": [
          {
            "x": 62,
            "y": 65
          },
          {
            "x": 74,
            "y": 65
          },
          {
            "x": 75,
            "y": 74
          },
          {
            "x": 62,
            "y": 75
          }
        ]
      },
      "confidence": 0.9982,
      "id": 11,
      "text": "3F"
    },
    {
      "boundingBox": {
        "vertices": [
          {
            "x": 76,
            "y": 65
          },
          {
            "x": 110,
            "y": 65
          },
          {
            "x": 110,
            "y": 74
          },
          {
            "x": 76,
            "y": 74
          }
        ]
      },
      "confidence": 0.9936,
      "id": 12,
      "text": "302.3호"
    },
    {
      "boundingBox": {
        "vertices": [
          {
            "x": 16,
            "y": 77
          },
          {
            "x": 29,
            "y": 77
          },
          {
            "x": 29,
            "y": 85
          },
          {
            "x": 16,
            "y": 85
          }
        ]
      },
      "confidence": 0.9951,
      "id": 13,
      "text": "HP"
    },
    {
      "boundingBox": {
        "vertices": [
          {
            "x": 30,
            "y": 76
          },
          {
            "x": 102,
            "y": 76
          },
          {
            "x": 102,
            "y": 86
          },
          {
            "x": 30,
            "y": 86
          }
        ]
      },
      "confidence": 0.9898,
      "id": 14,
      "text": ":010-3103-3420"
    },
    {
      "boundingBox": {
        "vertices": [
          {
            "x": 17,
            "y": 88
          },
          {
            "x": 43,
            "y": 88
          },
          {
            "x": 43,
            "y": 97
          },
          {
            "x": 17,
            "y": 97
          }
        ]
      },
      "confidence": 0.9983,
      "id": 15,
      "text": "Kakao"
    },
    {
      "boundingBox": {
        "vertices": [
          {
            "x": 45,
            "y": 89
          },
          {
            "x": 67,
            "y": 89
          },
          {
            "x": 67,
            "y": 97
          },
          {
            "x": 45,
            "y": 97
          }
        ]
      },
      "confidence": 0.977,
      "id": 16,
      "text": "story"
    },
    {
      "boundingBox": {
        "vertices": [
          {
            "x": 70,
            "y": 87
          },
          {
            "x": 78,
            "y": 87
          },
          {
            "x": 78,
            "y": 96
          },
          {
            "x": 70,
            "y": 96
          }
        ]
      },
      "confidence": 0.9605,
      "id": 17,
      "text": "D"
    },
    {
      "boundingBox": {
        "vertices": [
          {
            "x": 19,
            "y": 99
          },
          {
            "x": 89,
            "y": 98
          },
          {
            "x": 89,
            "y": 107
          },
          {
            "x": 19,
            "y": 108
          }
        ]
      },
      "confidence": 0.9209,
      "id": 18,
      "text": "anneshirlev0922"
    },
    {
      "boundingBox": {
        "vertices": [
          {
            "x": 90,
            "y": 98
          },
          {
            "x": 120,
            "y": 98
          },
          {
            "x": 120,
            "y": 107
          },
          {
            "x": 90,
            "y": 107
          }
        ]
      },
      "confidence": 0.9316,
      "id": 19,
      "text": "(사업자"
    },
    {
      "boundingBox": {
        "vertices": [
          {
            "x": 123,
            "y": 98
          },
          {
            "x": 150,
            "y": 98
          },
          {
            "x": 150,
            "y": 107
          },
          {
            "x": 123,
            "y": 107
          }
        ]
      },
      "confidence": 0.9672,
      "id": 20,
      "text": "확인후"
    },
    {
      "boundingBox": {
        "vertices": [
          {
            "x": 153,
            "y": 98
          },
          {
            "x": 176,
            "y": 98
          },
          {
            "x": 176,
            "y": 107
          },
          {
            "x": 153,
            "y": 107
          }
        ]
      },
      "confidence": 0.9702,
      "id": 21,
      "text": "가능)"
    },
    {
      "boundingBox": {
        "vertices": [
          {
            "x": 17,
            "y": 109
          },
          {
            "x": 58,
            "y": 110
          },
          {
            "x": 58,
            "y": 118
          },
          {
            "x": 17,
            "y": 118
          }
        ]
      },
      "confidence": 0.9784,
      "id": 22,
      "text": "instagram"
    },
    {
      "boundingBox": {
        "vertices": [
          {
            "x": 59,
            "y": 109
          },
          {
            "x": 112,
            "y": 109
          },
          {
            "x": 112,
            "y": 118
          },
          {
            "x": 59,
            "y": 118
          }
        ]
      },
      "confidence": 0.935,
      "id": 23,
      "text": ":anneshirley"
    },
    {
      "boundingBox": {
        "vertices": [
          {
            "x": 115,
            "y": 109
          },
          {
            "x": 143,
            "y": 109
          },
          {
            "x": 143,
            "y": 118
          },
          {
            "x": 115,
            "y": 118
          }
        ]
      },
      "confidence": 0.9956,
      "id": 24,
      "text": "official"
    },
    {
      "boundingBox": {
        "vertices": [
          {
            "x": 16,
            "y": 119
          },
          {
            "x": 52,
            "y": 119
          },
          {
            "x": 52,
            "y": 129
          },
          {
            "x": 16,
            "y": 129
          }
        ]
      },
      "confidence": 0.9665,
      "id": 25,
      "text": "\"판가는"
    },
    {
      "boundingBox": {
        "vertices": [
          {
            "x": 56,
            "y": 119
          },
          {
            "x": 90,
            "y": 119
          },
          {
            "x": 90,
            "y": 129
          },
          {
            "x": 56,
            "y": 129
          }
        ]
      },
      "confidence": 0.9877,
      "id": 26,
      "text": "도매가의"
    },
    {
      "boundingBox": {
        "vertices": [
          {
            "x": 93,
            "y": 119
          },
          {
            "x": 140,
            "y": 119
          },
          {
            "x": 140,
            "y": 129
          },
          {
            "x": 93,
            "y": 129
          }
        ]
      },
      "confidence": 0.9865,
      "id": 27,
      "text": "1.6배입니다"
    },
    {
      "boundingBox": {
        "vertices": [
          {
            "x": 17,
            "y": 130
          },
          {
            "x": 43,
            "y": 130
          },
          {
            "x": 43,
            "y": 140
          },
          {
            "x": 17,
            "y": 140
          }
        ]
      },
      "confidence": 0.9896,
      "id": 28,
      "text": "반드시"
    },
    {
      "boundingBox": {
        "vertices": [
          {
            "x": 46,
            "y": 130
          },
          {
            "x": 99,
            "y": 130
          },
          {
            "x": 99,
            "y": 140
          },
          {
            "x": 46,
            "y": 140
          }
        ]
      },
      "confidence": 0.9722,
      "id": 29,
      "text": "지켜주세요**"
    },
    {
      "boundingBox": {
        "vertices": [
          {
            "x": 16,
            "y": 141
          },
          {
            "x": 43,
            "y": 141
          },
          {
            "x": 43,
            "y": 151
          },
          {
            "x": 16,
            "y": 151
          }
        ]
      },
      "confidence": 0.985,
      "id": 30,
      "text": "본사의"
    },
    {
      "boundingBox": {
        "vertices": [
          {
            "x": 46,
            "y": 141
          },
          {
            "x": 82,
            "y": 141
          },
          {
            "x": 82,
            "y": 151
          },
          {
            "x": 46,
            "y": 151
          }
        ]
      },
      "confidence": 0.9901,
      "id": 31,
      "text": "도매거래"
    },
    {
      "boundingBox": {
        "vertices": [
          {
            "x": 85,
            "y": 141
          },
          {
            "x": 129,
            "y": 141
          },
          {
            "x": 129,
            "y": 151
          },
          {
            "x": 85,
            "y": 151
          }
        ]
      },
      "confidence": 0.9887,
      "id": 32,
      "text": "규칙위반시"
    },
    {
      "boundingBox": {
        "vertices": [
          {
            "x": 133,
            "y": 141
          },
          {
            "x": 193,
            "y": 140
          },
          {
            "x": 193,
            "y": 151
          },
          {
            "x": 133,
            "y": 152
          }
        ]
      },
      "confidence": 0.9641,
      "id": 33,
      "text": "법적대응합니다"
    },
    {
      "boundingBox": {
        "vertices": [
          {
            "x": 19,
            "y": 152
          },
          {
            "x": 79,
            "y": 152
          },
          {
            "x": 79,
            "y": 161
          },
          {
            "x": 19,
            "y": 161
          }
        ]
      },
      "confidence": 0.772,
      "id": 34,
      "text": "(본부카스기재)"
    },
    {
      "boundingBox": {
        "vertices": [
          {
            "x": 82,
            "y": 152
          },
          {
            "x": 133,
            "y": 152
          },
          {
            "x": 133,
            "y": 161
          },
          {
            "x": 82,
            "y": 161
          }
        ]
      },
      "confidence": 0.7423,
      "id": 35,
      "text": "한음법무법인"
    },
    {
      "boundingBox": {
        "vertices": [
          {
            "x": 16,
            "y": 175
          },
          {
            "x": 79,
            "y": 174
          },
          {
            "x": 80,
            "y": 186
          },
          {
            "x": 16,
            "y": 188
          }
        ]
      },
      "confidence": 0.9793,
      "id": 36,
      "text": "24-10-07(월)"
    },
    {
      "boundingBox": {
        "vertices": [
          {
            "x": 190,
            "y": 175
          },
          {
            "x": 230,
            "y": 175
          },
          {
            "x": 230,
            "y": 186
          },
          {
            "x": 190,
            "y": 186
          }
        ]
      },
      "confidence": 0.9897,
      "id": 37,
      "text": "336,100"
    },
    {
      "boundingBox": {
        "vertices": [
          {
            "x": 265,
            "y": 174
          },
          {
            "x": 286,
            "y": 174
          },
          {
            "x": 286,
            "y": 185
          },
          {
            "x": 265,
            "y": 185
          }
        ]
      },
      "confidence": 0.9971,
      "id": 38,
      "text": "청구"
    },
    {
      "boundingBox": {
        "vertices": [
          {
            "x": 66,
            "y": 198
          },
          {
            "x": 84,
            "y": 198
          },
          {
            "x": 84,
            "y": 209
          },
          {
            "x": 66,
            "y": 208
          }
        ]
      },
      "confidence": 0.9846,
      "id": 39,
      "text": "품명"
    },
    {
      "boundingBox": {
        "vertices": [
          {
            "x": 173,
            "y": 198
          },
          {
            "x": 191,
            "y": 198
          },
          {
            "x": 191,
            "y": 209
          },
          {
            "x": 173,
            "y": 209
          }
        ]
      },
      "confidence": 0.9895,
      "id": 40,
      "text": "단가"
    },
    {
      "boundingBox": {
        "vertices": [
          {
            "x": 203,
            "y": 198
          },
          {
            "x": 221,
            "y": 198
          },
          {
            "x": 221,
            "y": 209
          },
          {
            "x": 203,
            "y": 209
          }
        ]
      },
      "confidence": 0.995,
      "id": 41,
      "text": "수량"
    },
    {
      "boundingBox": {
        "vertices": [
          {
            "x": 267,
            "y": 197
          },
          {
            "x": 285,
            "y": 197
          },
          {
            "x": 285,
            "y": 208
          },
          {
            "x": 267,
            "y": 208
          }
        ]
      },
      "confidence": 0.993,
      "id": 42,
      "text": "금액"
    },
    {
      "boundingBox": {
        "vertices": [
          {
            "x": 16,
            "y": 220
          },
          {
            "x": 96,
            "y": 220
          },
          {
            "x": 96,
            "y": 231
          },
          {
            "x": 16,
            "y": 230
          }
        ]
      },
      "confidence": 0.9751,
      "id": 43,
      "text": "래빗드레스/래빗/m"
    },
    {
      "boundingBox": {
        "vertices": [
          {
            "x": 161,
            "y": 231
          },
          {
            "x": 192,
            "y": 231
          },
          {
            "x": 192,
            "y": 241
          },
          {
            "x": 161,
            "y": 241
          }
        ]
      },
      "confidence": 0.9848,
      "id": 44,
      "text": "29,000"
    },
    {
      "boundingBox": {
        "vertices": [
          {
            "x": 215,
            "y": 232
          },
          {
            "x": 221,
            "y": 231
          },
          {
            "x": 222,
            "y": 240
          },
          {
            "x": 215,
            "y": 240
          }
        ]
      },
      "confidence": 0.9711,
      "id": 45,
      "text": "1"
    },
    {
      "boundingBox": {
        "vertices": [
          {
            "x": 255,
            "y": 231
          },
          {
            "x": 286,
            "y": 231
          },
          {
            "x": 286,
            "y": 241
          },
          {
            "x": 255,
            "y": 241
          }
        ]
      },
      "confidence": 0.9815,
      "id": 46,
      "text": "29,000"
    },
    {
      "boundingBox": {
        "vertices": [
          {
            "x": 17,
            "y": 253
          },
          {
            "x": 120,
            "y": 253
          },
          {
            "x": 120,
            "y": 263
          },
          {
            "x": 17,
            "y": 263
          }
        ]
      },
      "confidence": 0.9803,
      "id": 47,
      "text": "마릴라슈트/도트(민트)/m"
    },
    {
      "boundingBox": {
        "vertices": [
          {
            "x": 161,
            "y": 264
          },
          {
            "x": 192,
            "y": 264
          },
          {
            "x": 192,
            "y": 274
          },
          {
            "x": 161,
            "y": 274
          }
        ]
      },
      "confidence": 0.9861,
      "id": 48,
      "text": "24,000"
    },
    {
      "boundingBox": {
        "vertices": [
          {
            "x": 215,
            "y": 265
          },
          {
            "x": 221,
            "y": 264
          },
          {
            "x": 222,
            "y": 273
          },
          {
            "x": 215,
            "y": 273
          }
        ]
      },
      "confidence": 0.9789,
      "id": 49,
      "text": "1"
    },
    {
      "boundingBox": {
        "vertices": [
          {
            "x": 255,
            "y": 264
          },
          {
            "x": 286,
            "y": 264
          },
          {
            "x": 286,
            "y": 274
          },
          {
            "x": 255,
            "y": 274
          }
        ]
      },
      "confidence": 0.9883,
      "id": 50,
      "text": "24,000"
    },
    {
      "boundingBox": {
        "vertices": [
          {
            "x": 17,
            "y": 286
          },
          {
            "x": 92,
            "y": 286
          },
          {
            "x": 92,
            "y": 296
          },
          {
            "x": 17,
            "y": 296
          }
        ]
      },
      "confidence": 0.8852,
      "id": 51,
      "text": "벨르터들넥/소라/s"
    },
    {
      "boundingBox": {
        "vertices": [
          {
            "x": 166,
            "y": 297
          },
          {
            "x": 191,
            "y": 297
          },
          {
            "x": 191,
            "y": 307
          },
          {
            "x": 166,
            "y": 307
          }
        ]
      },
      "confidence": 0.9662,
      "id": 52,
      "text": "8,000"
    },
    {
      "boundingBox": {
        "vertices": [
          {
            "x": 215,
            "y": 298
          },
          {
            "x": 221,
            "y": 297
          },
          {
            "x": 222,
            "y": 306
          },
          {
            "x": 215,
            "y": 306
          }
        ]
      },
      "confidence": 0.9936,
      "id": 53,
      "text": "1"
    },
    {
      "boundingBox": {
        "vertices": [
          {
            "x": 260,
            "y": 297
          },
          {
            "x": 285,
            "y": 297
          },
          {
            "x": 285,
            "y": 307
          },
          {
            "x": 260,
            "y": 307
          }
        ]
      },
      "confidence": 0.9284,
      "id": 54,
      "text": "8,000"
    },
    {
      "boundingBox": {
        "vertices": [
          {
            "x": 17,
            "y": 308
          },
          {
            "x": 95,
            "y": 307
          },
          {
            "x": 95,
            "y": 318
          },
          {
            "x": 17,
            "y": 318
          }
        ]
      },
      "confidence": 0.8798,
      "id": 55,
      "text": "벨르터들넥/소라/m"
    },
    {
      "boundingBox": {
        "vertices": [
          {
            "x": 166,
            "y": 319
          },
          {
            "x": 191,
            "y": 319
          },
          {
            "x": 191,
            "y": 329
          },
          {
            "x": 166,
            "y": 329
          }
        ]
      },
      "confidence": 0.9575,
      "id": 56,
      "text": "8.000"
    },
    {
      "boundingBox": {
        "vertices": [
          {
            "x": 215,
            "y": 320
          },
          {
            "x": 221,
            "y": 319
          },
          {
            "x": 221,
            "y": 328
          },
          {
            "x": 215,
            "y": 328
          }
        ]
      },
      "confidence": 0.9631,
      "id": 57,
      "text": "1"
    },
    {
      "boundingBox": {
        "vertices": [
          {
            "x": 260,
            "y": 319
          },
          {
            "x": 285,
            "y": 319
          },
          {
            "x": 285,
            "y": 329
          },
          {
            "x": 260,
            "y": 329
          }
        ]
      },
      "confidence": 0.9618,
      "id": 58,
      "text": "8.000"
    },
    {
      "boundingBox": {
        "vertices": [
          {
            "x": 17,
            "y": 340
          },
          {
            "x": 105,
            "y": 341
          },
          {
            "x": 105,
            "y": 351
          },
          {
            "x": 17,
            "y": 351
          }
        ]
      },
      "confidence": 0.9621,
      "id": 59,
      "text": "※안나드레스/블랙/m"
    },
    {
      "boundingBox": {
        "vertices": [
          {
            "x": 162,
            "y": 352
          },
          {
            "x": 192,
            "y": 352
          },
          {
            "x": 192,
            "y": 362
          },
          {
            "x": 162,
            "y": 362
          }
        ]
      },
      "confidence": 0.8752,
      "id": 60,
      "text": "23.000"
    },
    {
      "boundingBox": {
        "vertices": [
          {
            "x": 215,
            "y": 352
          },
          {
            "x": 222,
            "y": 352
          },
          {
            "x": 222,
            "y": 361
          },
          {
            "x": 215,
            "y": 361
          }
        ]
      },
      "confidence": 0.9956,
      "id": 61,
      "text": "2"
    },
    {
      "boundingBox": {
        "vertices": [
          {
            "x": 256,
            "y": 352
          },
          {
            "x": 286,
            "y": 352
          },
          {
            "x": 286,
            "y": 362
          },
          {
            "x": 256,
            "y": 362
          }
        ]
      },
      "confidence": 0.8888,
      "id": 62,
      "text": "46,000"
    },
    {
      "boundingBox": {
        "vertices": [
          {
            "x": 17,
            "y": 373
          },
          {
            "x": 145,
            "y": 374
          },
          {
            "x": 144,
            "y": 385
          },
          {
            "x": 17,
            "y": 384
          }
        ]
      },
      "confidence": 0.9836,
      "id": 63,
      "text": "※퓨어레이스원피스슈트/크림/s"
    },
    {
      "boundingBox": {
        "vertices": [
          {
            "x": 162,
            "y": 385
          },
          {
            "x": 192,
            "y": 385
          },
          {
            "x": 192,
            "y": 394
          },
          {
            "x": 162,
            "y": 394
          }
        ]
      },
      "confidence": 0.9015,
      "id": 64,
      "text": "27,000"
    },
    {
      "boundingBox": {
        "vertices": [
          {
            "x": 215,
            "y": 386
          },
          {
            "x": 221,
            "y": 386
          },
          {
            "x": 221,
            "y": 394
          },
          {
            "x": 215,
            "y": 394
          }
        ]
      },
      "confidence": 0.969,
      "id": 65,
      "text": "1"
    },
    {
      "boundingBox": {
        "vertices": [
          {
            "x": 255,
            "y": 385
          },
          {
            "x": 286,
            "y": 385
          },
          {
            "x": 286,
            "y": 395
          },
          {
            "x": 255,
            "y": 395
          }
        ]
      },
      "confidence": 0.9089,
      "id": 66,
      "text": "27,000"
    },
    {
      "boundingBox": {
        "vertices": [
          {
            "x": 32,
            "y": 406
          },
          {
            "x": 65,
            "y": 406
          },
          {
            "x": 65,
            "y": 416
          },
          {
            "x": 32,
            "y": 416
          }
        ]
      },
      "confidence": 0.9895,
      "id": 67,
      "text": "판매소계"
    },
    {
      "boundingBox": {
        "vertices": [
          {
            "x": 176,
            "y": 407
          },
          {
            "x": 191,
            "y": 407
          },
          {
            "x": 191,
            "y": 416
          },
          {
            "x": 176,
            "y": 417
          }
        ]
      },
      "confidence": 0.8653,
      "id": 68,
      "text": "6건"
    },
    {
      "boundingBox": {
        "vertices": [
          {
            "x": 214,
            "y": 407
          },
          {
            "x": 222,
            "y": 407
          },
          {
            "x": 222,
            "y": 416
          },
          {
            "x": 214,
            "y": 416
          }
        ]
      },
      "confidence": 0.9894,
      "id": 69,
      "text": "7"
    },
    {
      "boundingBox": {
        "vertices": [
          {
            "x": 251,
            "y": 407
          },
          {
            "x": 286,
            "y": 407
          },
          {
            "x": 286,
            "y": 417
          },
          {
            "x": 251,
            "y": 417
          }
        ]
      },
      "confidence": 0.9315,
      "id": 70,
      "text": "142.000"
    },
    {
      "boundingBox": {
        "vertices": [
          {
            "x": 58,
            "y": 433
          },
          {
            "x": 68,
            "y": 433
          },
          {
            "x": 68,
            "y": 444
          },
          {
            "x": 58,
            "y": 444
          }
        ]
      },
      "confidence": 0.963,
      "id": 71,
      "text": "전"
    },
    {
      "boundingBox": {
        "vertices": [
          {
            "x": 87,
            "y": 433
          },
          {
            "x": 101,
            "y": 433
          },
          {
            "x": 101,
            "y": 444
          },
          {
            "x": 87,
            "y": 444
          }
        ]
      },
      "confidence": 0.9291,
      "id": 72,
      "text": "잔:"
    },
    {
      "boundingBox": {
        "vertices": [
          {
            "x": 228,
            "y": 434
          },
          {
            "x": 267,
            "y": 434
          },
          {
            "x": 267,
            "y": 445
          },
          {
            "x": 228,
            "y": 445
          }
        ]
      },
      "confidence": 0.9773,
      "id": 73,
      "text": "208,300"
    },
    {
      "boundingBox": {
        "vertices": [
          {
            "x": 58,
            "y": 446
          },
          {
            "x": 101,
            "y": 446
          },
          {
            "x": 101,
            "y": 457
          },
          {
            "x": 58,
            "y": 457
          }
        ]
      },
      "confidence": 0.9587,
      "id": 74,
      "text": "당일합계:"
    },
    {
      "boundingBox": {
        "vertices": [
          {
            "x": 228,
            "y": 447
          },
          {
            "x": 267,
            "y": 447
          },
          {
            "x": 267,
            "y": 458
          },
          {
            "x": 228,
            "y": 458
          }
        ]
      },
      "confidence": 0.9833,
      "id": 75,
      "text": "142,000"
    },
    {
      "boundingBox": {
        "vertices": [
          {
            "x": 58,
            "y": 458
          },
          {
            "x": 101,
            "y": 458
          },
          {
            "x": 101,
            "y": 470
          },
          {
            "x": 58,
            "y": 470
          }
        ]
      },
      "confidence": 0.9741,
      "id": 76,
      "text": "할인금액:"
    },
    {
      "boundingBox": {
        "vertices": [
          {
            "x": 234,
            "y": 460
          },
          {
            "x": 267,
            "y": 460
          },
          {
            "x": 267,
            "y": 471
          },
          {
            "x": 234,
            "y": 471
          }
        ]
      },
      "confidence": 0.9892,
      "id": 77,
      "text": "14200"
    },
    {
      "boundingBox": {
        "vertices": [
          {
            "x": 58,
            "y": 472
          },
          {
            "x": 69,
            "y": 472
          },
          {
            "x": 69,
            "y": 483
          },
          {
            "x": 58,
            "y": 483
          }
        ]
      },
      "confidence": 0.9822,
      "id": 78,
      "text": "당"
    },
    {
      "boundingBox": {
        "vertices": [
          {
            "x": 87,
            "y": 472
          },
          {
            "x": 101,
            "y": 472
          },
          {
            "x": 102,
            "y": 483
          },
          {
            "x": 87,
            "y": 483
          }
        ]
      },
      "confidence": 0.8961,
      "id": 79,
      "text": "잔:"
    },
    {
      "boundingBox": {
        "vertices": [
          {
            "x": 228,
            "y": 473
          },
          {
            "x": 267,
            "y": 474
          },
          {
            "x": 267,
            "y": 484
          },
          {
            "x": 228,
            "y": 483
          }
        ]
      },
      "confidence": 0.921,
      "id": 80,
      "text": "336,100"
    },
    {
      "boundingBox": {
        "vertices": [
          {
            "x": 58,
            "y": 495
          },
          {
            "x": 101,
            "y": 495
          },
          {
            "x": 101,
            "y": 507
          },
          {
            "x": 58,
            "y": 507
          }
        ]
      },
      "confidence": 0.9502,
      "id": 81,
      "text": "매입전잔:"
    },
    {
      "boundingBox": {
        "vertices": [
          {
            "x": 259,
            "y": 498
          },
          {
            "x": 267,
            "y": 498
          },
          {
            "x": 267,
            "y": 507
          },
          {
            "x": 259,
            "y": 507
          }
        ]
      },
      "confidence": 0.9955,
      "id": 82,
      "text": "0"
    },
    {
      "boundingBox": {
        "vertices": [
          {
            "x": 58,
            "y": 509
          },
          {
            "x": 101,
            "y": 509
          },
          {
            "x": 101,
            "y": 520
          },
          {
            "x": 58,
            "y": 520
          }
        ]
      },
      "confidence": 0.9788,
      "id": 83,
      "text": "매입잔액:"
    },
    {
      "boundingBox": {
        "vertices": [
          {
            "x": 259,
            "y": 510
          },
          {
            "x": 267,
            "y": 511
          },
          {
            "x": 267,
            "y": 520
          },
          {
            "x": 259,
            "y": 520
          }
        ]
      },
      "confidence": 0.9965,
      "id": 84,
      "text": "0"
    },
    {
      "boundingBox": {
        "vertices": [
          {
            "x": 17,
            "y": 533
          },
          {
            "x": 27,
            "y": 533
          },
          {
            "x": 27,
            "y": 542
          },
          {
            "x": 17,
            "y": 542
          }
        ]
      },
      "confidence": 0.6856,
      "id": 85,
      "text": "※"
    },
    {
      "boundingBox": {
        "vertices": [
          {
            "x": 28,
            "y": 533
          },
          {
            "x": 55,
            "y": 533
          },
          {
            "x": 55,
            "y": 543
          },
          {
            "x": 28,
            "y": 543
          }
        ]
      },
      "confidence": 0.9955,
      "id": 86,
      "text": "표시는"
    },
    {
      "boundingBox": {
        "vertices": [
          {
            "x": 58,
            "y": 532
          },
          {
            "x": 121,
            "y": 532
          },
          {
            "x": 121,
            "y": 543
          },
          {
            "x": 58,
            "y": 543
          }
        ]
      },
      "confidence": 0.9845,
      "id": 87,
      "text": "미송상품입니다."
    },
    {
      "boundingBox": {
        "vertices": [
          {
            "x": 16,
            "y": 555
          },
          {
            "x": 47,
            "y": 555
          },
          {
            "x": 47,
            "y": 565
          },
          {
            "x": 16,
            "y": 565
          }
        ]
      },
      "confidence": 0.9157,
      "id": 88,
      "text": "*입금은"
    },
    {
      "boundingBox": {
        "vertices": [
          {
            "x": 51,
            "y": 555
          },
          {
            "x": 77,
            "y": 555
          },
          {
            "x": 77,
            "y": 565
          },
          {
            "x": 51,
            "y": 565
          }
        ]
      },
      "confidence": 0.9891,
      "id": 89,
      "text": "반드시"
    },
    {
      "boundingBox": {
        "vertices": [
          {
            "x": 81,
            "y": 555
          },
          {
            "x": 124,
            "y": 555
          },
          {
            "x": 124,
            "y": 565
          },
          {
            "x": 81,
            "y": 565
          }
        ]
      },
      "confidence": 0.9949,
      "id": 90,
      "text": "상호명으로"
    },
    {
      "boundingBox": {
        "vertices": [
          {
            "x": 128,
            "y": 554
          },
          {
            "x": 179,
            "y": 554
          },
          {
            "x": 179,
            "y": 565
          },
          {
            "x": 128,
            "y": 565
          }
        ]
      },
      "confidence": 0.9857,
      "id": 91,
      "text": "입금해주세요"
    },
    {
      "boundingBox": {
        "vertices": [
          {
            "x": 16,
            "y": 566
          },
          {
            "x": 64,
            "y": 566
          },
          {
            "x": 64,
            "y": 576
          },
          {
            "x": 16,
            "y": 576
          }
        ]
      },
      "confidence": 0.978,
      "id": 92,
      "text": "*세금계산서"
    },
    {
      "boundingBox": {
        "vertices": [
          {
            "x": 67,
            "y": 566
          },
          {
            "x": 92,
            "y": 566
          },
          {
            "x": 92,
            "y": 575
          },
          {
            "x": 67,
            "y": 575
          }
        ]
      },
      "confidence": 0.9911,
      "id": 93,
      "text": "100%"
    },
    {
      "boundingBox": {
        "vertices": [
          {
            "x": 95,
            "y": 566
          },
          {
            "x": 112,
            "y": 566
          },
          {
            "x": 112,
            "y": 576
          },
          {
            "x": 95,
            "y": 576
          }
        ]
      },
      "confidence": 0.9935,
      "id": 94,
      "text": "발행"
    },
    {
      "boundingBox": {
        "vertices": [
          {
            "x": 16,
            "y": 577
          },
          {
            "x": 64,
            "y": 577
          },
          {
            "x": 64,
            "y": 587
          },
          {
            "x": 16,
            "y": 587
          }
        ]
      },
      "confidence": 0.9628,
      "id": 95,
      "text": "*상기금액은"
    },
    {
      "boundingBox": {
        "vertices": [
          {
            "x": 67,
            "y": 577
          },
          {
            "x": 94,
            "y": 577
          },
          {
            "x": 94,
            "y": 586
          },
          {
            "x": 67,
            "y": 586
          }
        ]
      },
      "confidence": 0.9789,
      "id": 96,
      "text": "부가세"
    },
    {
      "boundingBox": {
        "vertices": [
          {
            "x": 98,
            "y": 577
          },
          {
            "x": 115,
            "y": 577
          },
          {
            "x": 115,
            "y": 586
          },
          {
            "x": 98,
            "y": 586
          }
        ]
      },
      "confidence": 0.9605,
      "id": 97,
      "text": "별도"
    },
    {
      "boundingBox": {
        "vertices": [
          {
            "x": 118,
            "y": 576
          },
          {
            "x": 161,
            "y": 576
          },
          {
            "x": 161,
            "y": 586
          },
          {
            "x": 118,
            "y": 586
          }
        ]
      },
      "confidence": 0.9858,
      "id": 98,
      "text": "금액입니다"
    },
    {
      "boundingBox": {
        "vertices": [
          {
            "x": 17,
            "y": 588
          },
          {
            "x": 59,
            "y": 588
          },
          {
            "x": 59,
            "y": 597
          },
          {
            "x": 17,
            "y": 597
          }
        ]
      },
      "confidence": 0.8713,
      "id": 99,
      "text": "*VAT별도,"
    },
    {
      "boundingBox": {
        "vertices": [
          {
            "x": 62,
            "y": 587
          },
          {
            "x": 106,
            "y": 587
          },
          {
            "x": 106,
            "y": 597
          },
          {
            "x": 62,
            "y": 597
          }
        ]
      },
      "confidence": 0.9921,
      "id": 100,
      "text": "세금계산서"
    },
    {
      "boundingBox": {
        "vertices": [
          {
            "x": 110,
            "y": 587
          },
          {
            "x": 161,
            "y": 587
          },
          {
            "x": 161,
            "y": 598
          },
          {
            "x": 110,
            "y": 597
          }
        ]
      },
      "confidence": 0.9199,
      "id": 101,
      "text": "매월말일마감"
    },
    {
      "boundingBox": {
        "vertices": [
          {
            "x": 16,
            "y": 598
          },
          {
            "x": 54,
            "y": 598
          },
          {
            "x": 54,
            "y": 608
          },
          {
            "x": 16,
            "y": 608
          }
        ]
      },
      "confidence": 0.9514,
      "id": 102,
      "text": "(전자마감"
    },
    {
      "boundingBox": {
        "vertices": [
          {
            "x": 57,
            "y": 598
          },
          {
            "x": 97,
            "y": 598
          },
          {
            "x": 97,
            "y": 608
          },
          {
            "x": 57,
            "y": 608
          }
        ]
      },
      "confidence": 0.9839,
      "id": 103,
      "text": "수정불가)"
    },
    {
      "boundingBox": {
        "vertices": [
          {
            "x": 16,
            "y": 609
          },
          {
            "x": 42,
            "y": 609
          },
          {
            "x": 42,
            "y": 619
          },
          {
            "x": 16,
            "y": 619
          }
        ]
      },
      "confidence": 0.9958,
      "id": 104,
      "text": "계산서"
    },
    {
      "boundingBox": {
        "vertices": [
          {
            "x": 45,
            "y": 609
          },
          {
            "x": 80,
            "y": 609
          },
          {
            "x": 80,
            "y": 619
          },
          {
            "x": 45,
            "y": 619
          }
        ]
      },
      "confidence": 0.987,
      "id": 105,
      "text": "관련문의"
    },
    {
      "boundingBox": {
        "vertices": [
          {
            "x": 83,
            "y": 609
          },
          {
            "x": 110,
            "y": 609
          },
          {
            "x": 110,
            "y": 619
          },
          {
            "x": 83,
            "y": 619
          }
        ]
      },
      "confidence": 0.9885,
      "id": 106,
      "text": "담당자"
    },
    {
      "boundingBox": {
        "vertices": [
          {
            "x": 113,
            "y": 609
          },
          {
            "x": 181,
            "y": 609
          },
          {
            "x": 181,
            "y": 619
          },
          {
            "x": 113,
            "y": 619
          }
        ]
      },
      "confidence": 0.9947,
      "id": 107,
      "text": "010-3103-3420"
    },
    {
      "boundingBox": {
        "vertices": [
          {
            "x": 16,
            "y": 620
          },
          {
            "x": 39,
            "y": 620
          },
          {
            "x": 39,
            "y": 630
          },
          {
            "x": 16,
            "y": 630
          }
        ]
      },
      "confidence": 0.9036,
      "id": 108,
      "text": "*교환"
    },
    {
      "boundingBox": {
        "vertices": [
          {
            "x": 43,
            "y": 620
          },
          {
            "x": 86,
            "y": 620
          },
          {
            "x": 86,
            "y": 630
          },
          {
            "x": 43,
            "y": 630
          }
        ]
      },
      "confidence": 0.9871,
      "id": 109,
      "text": "일주일이내"
    },
    {
      "boundingBox": {
        "vertices": [
          {
            "x": 16,
            "y": 631
          },
          {
            "x": 42,
            "y": 631
          },
          {
            "x": 42,
            "y": 640
          },
          {
            "x": 16,
            "y": 640
          }
        ]
      },
      "confidence": 0.9861,
      "id": 110,
      "text": "<니트"
    },
    {
      "boundingBox": {
        "vertices": [
          {
            "x": 43,
            "y": 631
          },
          {
            "x": 148,
            "y": 631
          },
          {
            "x": 148,
            "y": 640
          },
          {
            "x": 43,
            "y": 640
          }
        ]
      },
      "confidence": 0.9574,
      "id": 111,
      "text": "화이트색상,시즌지난상품>"
    },
    {
      "boundingBox": {
        "vertices": [
          {
            "x": 16,
            "y": 641
          },
          {
            "x": 34,
            "y": 641
          },
          {
            "x": 34,
            "y": 651
          },
          {
            "x": 16,
            "y": 651
          }
        ]
      },
      "confidence": 0.9897,
      "id": 112,
      "text": "교환"
    },
    {
      "boundingBox": {
        "vertices": [
          {
            "x": 38,
            "y": 642
          },
          {
            "x": 47,
            "y": 642
          },
          {
            "x": 47,
            "y": 651
          },
          {
            "x": 38,
            "y": 651
          }
        ]
      },
      "confidence": 0.9971,
      "id": 113,
      "text": "및"
    },
    {
      "boundingBox": {
        "vertices": [
          {
            "x": 51,
            "y": 641
          },
          {
            "x": 69,
            "y": 641
          },
          {
            "x": 69,
            "y": 651
          },
          {
            "x": 51,
            "y": 651
          }
        ]
      },
      "confidence": 0.9701,
      "id": 114,
      "text": "환불"
    },
    {
      "boundingBox": {
        "vertices": [
          {
            "x": 72,
            "y": 641
          },
          {
            "x": 116,
            "y": 640
          },
          {
            "x": 116,
            "y": 651
          },
          {
            "x": 72,
            "y": 651
          }
        ]
      },
      "confidence": 0.9701,
      "id": 115,
      "text": "불가합니다"
    },
    {
      "boundingBox": {
        "vertices": [
          {
            "x": 16,
            "y": 652
          },
          {
            "x": 64,
            "y": 652
          },
          {
            "x": 64,
            "y": 662
          },
          {
            "x": 16,
            "y": 662
          }
        ]
      },
      "confidence": 0.9768,
      "id": 116,
      "text": "*매입금액은"
    },
    {
      "boundingBox": {
        "vertices": [
          {
            "x": 67,
            "y": 652
          },
          {
            "x": 98,
            "y": 652
          },
          {
            "x": 98,
            "y": 662
          },
          {
            "x": 67,
            "y": 662
          }
        ]
      },
      "confidence": 0.9674,
      "id": 117,
      "text": "2주이내"
    },
    {
      "boundingBox": {
        "vertices": [
          {
            "x": 102,
            "y": 652
          },
          {
            "x": 163,
            "y": 652
          },
          {
            "x": 163,
            "y": 662
          },
          {
            "x": 102,
            "y": 662
          }
        ]
      },
      "confidence": 0.9749,
      "id": 118,
      "text": "사용가능합니다"
    },
    {
      "boundingBox": {
        "vertices": [
          {
            "x": 16,
            "y": 663
          },
          {
            "x": 22,
            "y": 663
          },
          {
            "x": 22,
            "y": 670
          },
          {
            "x": 16,
            "y": 670
          }
        ]
      },
      "confidence": 0.7578,
      "id": 119,
      "text": "·"
    },
    {
      "boundingBox": {
        "vertices": [
          {
            "x": 24,
            "y": 663
          },
          {
            "x": 98,
            "y": 664
          },
          {
            "x": 98,
            "y": 674
          },
          {
            "x": 24,
            "y": 674
          }
        ]
      },
      "confidence": 0.9549,
      "id": 120,
      "text": "卸売規則事項です"
    },
    {
      "boundingBox": {
        "vertices": [
          {
            "x": 17,
            "y": 674
          },
          {
            "x": 104,
            "y": 674
          },
          {
            "x": 104,
            "y": 684
          },
          {
            "x": 17,
            "y": 684
          }
        ]
      },
      "confidence": 0.7698,
      "id": 121,
      "text": "交換及び返品資料は、"
    },
    {
      "boundingBox": {
        "vertices": [
          {
            "x": 109,
            "y": 674
          },
          {
            "x": 184,
            "y": 674
          },
          {
            "x": 184,
            "y": 684
          },
          {
            "x": 109,
            "y": 684
          }
        ]
      },
      "confidence": 0.9949,
      "id": 122,
      "text": "いかなる場合でも"
    },
    {
      "boundingBox": {
        "vertices": [
          {
            "x": 185,
            "y": 675
          },
          {
            "x": 240,
            "y": 674
          },
          {
            "x": 240,
            "y": 684
          },
          {
            "x": 185,
            "y": 684
          }
        ]
      },
      "confidence": 0.9456,
      "id": 123,
      "text": "お願いします"
    },
    {
      "boundingBox": {
        "vertices": [
          {
            "x": 17,
            "y": 686
          },
          {
            "x": 34,
            "y": 686
          },
          {
            "x": 34,
            "y": 695
          },
          {
            "x": 17,
            "y": 695
          }
        ]
      },
      "confidence": 0.8119,
      "id": 124,
      "text": "本社"
    },
    {
      "boundingBox": {
        "vertices": [
          {
            "x": 35,
            "y": 685
          },
          {
            "x": 119,
            "y": 685
          },
          {
            "x": 119,
            "y": 695
          },
          {
            "x": 35,
            "y": 695
          }
        ]
      },
      "confidence": 0.9686,
      "id": 125,
      "text": "で負担いたしません"
    },
    {
      "boundingBox": {
        "vertices": [
          {
            "x": 98,
            "y": 733
          },
          {
            "x": 168,
            "y": 733
          },
          {
            "x": 168,
            "y": 743
          },
          {
            "x": 98,
            "y": 743
          }
        ]
      },
      "confidence": 0.9919,
      "id": 126,
      "text": "24264654487996"
    }
  ],
  "metadata": {
    "pages": [
      {
        "height": 770,
        "width": 302,
        "page": 1
      }
    ]
  }
}