{
  "text": "영 수 증(공급받는자) \n기린 귀하 \n0048-재발행 2024-10-07(월)03:14:14 \nnr k \n남대문 크레용상가 278호 \nNamdaemun market \nSeoul crayonchildren 278 \n☎02.318.3197 \n☎010.2101.3197 \n☎010.4015.3197 \nkakaotalk: nrk1988 \nkakaostory 1 :nrk1988 \nkakaostory2:nrk2 \nkakaostory3:nrk1 \ninstagram: nrk.wholesale \ne-mail:nrk1988@naver.com \n24-10-07(월) 1,194,900 청구 \n품명 단가 수량 금액 \n23.ST시보리티/베이지/M \n9,000 1 9,000 \n※33.골덴팔부바지/베이지/S \n15,000 1 15,000 \n------------- \n33.골덴팔부바지/차콜/XL \n15,000 1 15,000 \n5.그라운드남방/아이보리/XL \n18,000 1 18,000 \n20.덴깡카라맨투맨/검정/4XL \n21,000 1 21,000 \n---------- \n※20.덴장카라맨투맨/핑크/S \n18,000 1 18,000 \n--------------- \n※20.덴깡카라맨투맨/핑크/M \n18,000 1 18,000 \n8.면카라니트/검정/L \n22,000 2 44,000 \n15.버디단가라세트/레드/L \n23,000 1 23,000 \n--------- \n※15.버디단가라세트/파랑/L \n23,000 1 23,000 \n25.보데티/네이비/S \n10,000 1 10,000 \n----- \n25.보데티/아이/S \n10,000 1 10,000 \n9.스쿨룩조끼/아이/XS \n18,000 1 18,000 \n---------- \n9.스쿨룩조끼/아이/4XL \n21,000 1 21,000 \n※14.어텀테이프세트/메란지/M \n25,000 1 25,000 \n-------- \n※14.어텀테이프세트/메란지/XL \n25,000 1 25,000 \n21.와플테입티/곤색/S \n16,000 1 16,000 \n32.주름팔부바지/메란지/S \n17,000 1 17,000 \n----------- \n32.주름팔부바지/메란지/M \n17,000 1 17,000 \n26.트렌디시보리티/와인/M \n12,000 1 12,000 \n16.파리카라세트/백메란지/4XL \n26,000 1 26,000 \n※12.팔팔상하세트/네이비/XL \n22,000 1 22,000 \n----------------- \n12.팔팔상하세트/크림/2XL \n25,000 1 25,000 \n-------- \n12.팔팔상하세트/크림/L \n22,000 1 22,000 \n------ \n※12팔팔상하세트/크림/S \n22,000 1 22,000 \n7.피셔맨니트/네이비/L \n25,000 1 25,000 \n판매소계 26건 27 517,000 \n전 잔: 729,600 \n당일합계: 517,000 \n할인금액: 51,700 \n당 잔: 1,194,900 \n매입전잔: 0 \n매입잔액: \n※ 1차 \n※ 표시는 미송상품입니다. \n==== \n*입금처:국민은행016702-04-566291(김누리) \n*상기금액은 부가세별도 금액입니다. \n*샘플은 2주이내에 미반납시 청구처리됩니다. \n*아이보리, 백색 교환 반품 되지 않습니다. \n*세금계산서 매월 10일까지 발행됩니다. \n23216486313339",
  "confidence": 0.9773,
  "words": [
    {
      "boundingBox": {
        "vertices": [
          {
            "x": 69,
            "y": 2
          },
          {
            "x": 87,
            "y": 2
          },
          {
            "x": 87,
            "y": 23
          },
          {
            "x": 69,
            "y": 23
          }
        ]
      },
      "confidence": 0.97,
      "id": 0,
      "text": "영"
    },
    {
      "boundingBox": {
        "vertices": [
          {
            "x": 92,
            "y": 3
          },
          {
            "x": 111,
            "y": 2
          },
          {
            "x": 112,
            "y": 23
          },
          {
            "x": 92,
            "y": 23
          }
        ]
      },
      "confidence": 0.9665,
      "id": 1,
      "text": "수"
    },
    {
      "boundingBox": {
        "vertices": [
          {
            "x": 117,
            "y": 3
          },
          {
            "x": 208,
            "y": 3
          },
          {
            "x": 208,
            "y": 23
          },
          {
            "x": 117,
            "y": 23
          }
        ]
      },
      "confidence": 0.9791,
      "id": 2,
      "text": "증(공급받는자)"
    },
    {
      "boundingBox": {
        "vertices": [
          {
            "x": 188,
            "y": 28
          },
          {
            "x": 226,
            "y": 28
          },
          {
            "x": 226,
            "y": 51
          },
          {
            "x": 188,
            "y": 51
          }
        ]
      },
      "confidence": 0.9865,
      "id": 3,
      "text": "기린"
    },
    {
      "boundingBox": {
        "vertices": [
          {
            "x": 232,
            "y": 33
          },
          {
            "x": 258,
            "y": 33
          },
          {
            "x": 258,
            "y": 48
          },
          {
            "x": 232,
            "y": 48
          }
        ]
      },
      "confidence": 0.9918,
      "id": 4,
      "text": "귀하"
    },
    {
      "boundingBox": {
        "vertices": [
          {
            "x": 10,
            "y": 53
          },
          {
            "x": 82,
            "y": 53
          },
          {
            "x": 82,
            "y": 69
          },
          {
            "x": 10,
            "y": 69
          }
        ]
      },
      "confidence": 0.9303,
      "id": 5,
      "text": "0048-재발행"
    },
    {
      "boundingBox": {
        "vertices": [
          {
            "x": 131,
            "y": 54
          },
          {
            "x": 266,
            "y": 54
          },
          {
            "x": 266,
            "y": 70
          },
          {
            "x": 131,
            "y": 70
          }
        ]
      },
      "confidence": 0.9775,
      "id": 6,
      "text": "2024-10-07(월)03:14:14"
    },
    {
      "boundingBox": {
        "vertices": [
          {
            "x": 117,
            "y": 87
          },
          {
            "x": 146,
            "y": 87
          },
          {
            "x": 146,
            "y": 104
          },
          {
            "x": 117,
            "y": 104
          }
        ]
      },
      "confidence": 0.8934,
      "id": 7,
      "text": "nr"
    },
    {
      "boundingBox": {
        "vertices": [
          {
            "x": 147,
            "y": 86
          },
          {
            "x": 161,
            "y": 86
          },
          {
            "x": 161,
            "y": 104
          },
          {
            "x": 147,
            "y": 104
          }
        ]
      },
      "confidence": 0.9949,
      "id": 8,
      "text": "k"
    },
    {
      "boundingBox": {
        "vertices": [
          {
            "x": 12,
            "y": 108
          },
          {
            "x": 50,
            "y": 108
          },
          {
            "x": 50,
            "y": 124
          },
          {
            "x": 12,
            "y": 124
          }
        ]
      },
      "confidence": 0.9687,
      "id": 9,
      "text": "남대문"
    },
    {
      "boundingBox": {
        "vertices": [
          {
            "x": 51,
            "y": 108
          },
          {
            "x": 114,
            "y": 108
          },
          {
            "x": 114,
            "y": 123
          },
          {
            "x": 51,
            "y": 123
          }
        ]
      },
      "confidence": 0.9855,
      "id": 10,
      "text": "크레용상가"
    },
    {
      "boundingBox": {
        "vertices": [
          {
            "x": 114,
            "y": 108
          },
          {
            "x": 150,
            "y": 108
          },
          {
            "x": 150,
            "y": 123
          },
          {
            "x": 114,
            "y": 123
          }
        ]
      },
      "confidence": 0.9929,
      "id": 11,
      "text": "278호"
    },
    {
      "boundingBox": {
        "vertices": [
          {
            "x": 10,
            "y": 125
          },
          {
            "x": 86,
            "y": 126
          },
          {
            "x": 85,
            "y": 140
          },
          {
            "x": 10,
            "y": 140
          }
        ]
      },
      "confidence": 0.9637,
      "id": 12,
      "text": "Namdaemun"
    },
    {
      "boundingBox": {
        "vertices": [
          {
            "x": 86,
            "y": 126
          },
          {
            "x": 128,
            "y": 126
          },
          {
            "x": 128,
            "y": 140
          },
          {
            "x": 86,
            "y": 140
          }
        ]
      },
      "confidence": 0.9967,
      "id": 13,
      "text": "market"
    },
    {
      "boundingBox": {
        "vertices": [
          {
            "x": 11,
            "y": 143
          },
          {
            "x": 44,
            "y": 143
          },
          {
            "x": 44,
            "y": 157
          },
          {
            "x": 11,
            "y": 157
          }
        ]
      },
      "confidence": 0.9942,
      "id": 14,
      "text": "Seoul"
    },
    {
      "boundingBox": {
        "vertices": [
          {
            "x": 45,
            "y": 143
          },
          {
            "x": 127,
            "y": 143
          },
          {
            "x": 127,
            "y": 158
          },
          {
            "x": 45,
            "y": 158
          }
        ]
      },
      "confidence": 0.9598,
      "id": 15,
      "text": "crayonchildren"
    },
    {
      "boundingBox": {
        "vertices": [
          {
            "x": 127,
            "y": 143
          },
          {
            "x": 152,
            "y": 143
          },
          {
            "x": 152,
            "y": 157
          },
          {
            "x": 127,
            "y": 157
          }
        ]
      },
      "confidence": 0.995,
      "id": 16,
      "text": "278"
    },
    {
      "boundingBox": {
        "vertices": [
          {
            "x": 11,
            "y": 159
          },
          {
            "x": 90,
            "y": 158
          },
          {
            "x": 90,
            "y": 173
          },
          {
            "x": 12,
            "y": 174
          }
        ]
      },
      "confidence": 0.9773,
      "id": 17,
      "text": "☎02.318.3197"
    },
    {
      "boundingBox": {
        "vertices": [
          {
            "x": 11,
            "y": 176
          },
          {
            "x": 104,
            "y": 175
          },
          {
            "x": 104,
            "y": 189
          },
          {
            "x": 11,
            "y": 190
          }
        ]
      },
      "confidence": 0.9837,
      "id": 18,
      "text": "☎010.2101.3197"
    },
    {
      "boundingBox": {
        "vertices": [
          {
            "x": 11,
            "y": 193
          },
          {
            "x": 104,
            "y": 192
          },
          {
            "x": 104,
            "y": 207
          },
          {
            "x": 11,
            "y": 208
          }
        ]
      },
      "confidence": 0.9844,
      "id": 19,
      "text": "☎010.4015.3197"
    },
    {
      "boundingBox": {
        "vertices": [
          {
            "x": 10,
            "y": 209
          },
          {
            "x": 72,
            "y": 209
          },
          {
            "x": 72,
            "y": 223
          },
          {
            "x": 10,
            "y": 223
          }
        ]
      },
      "confidence": 0.9677,
      "id": 20,
      "text": "kakaotalk:"
    },
    {
      "boundingBox": {
        "vertices": [
          {
            "x": 72,
            "y": 210
          },
          {
            "x": 120,
            "y": 210
          },
          {
            "x": 120,
            "y": 223
          },
          {
            "x": 72,
            "y": 223
          }
        ]
      },
      "confidence": 0.99,
      "id": 21,
      "text": "nrk1988"
    },
    {
      "boundingBox": {
        "vertices": [
          {
            "x": 10,
            "y": 225
          },
          {
            "x": 72,
            "y": 227
          },
          {
            "x": 72,
            "y": 242
          },
          {
            "x": 10,
            "y": 241
          }
        ]
      },
      "confidence": 0.9771,
      "id": 22,
      "text": "kakaostory"
    },
    {
      "boundingBox": {
        "vertices": [
          {
            "x": 72,
            "y": 228
          },
          {
            "x": 81,
            "y": 228
          },
          {
            "x": 81,
            "y": 240
          },
          {
            "x": 72,
            "y": 240
          }
        ]
      },
      "confidence": 0.9621,
      "id": 23,
      "text": "1"
    },
    {
      "boundingBox": {
        "vertices": [
          {
            "x": 82,
            "y": 226
          },
          {
            "x": 139,
            "y": 226
          },
          {
            "x": 139,
            "y": 241
          },
          {
            "x": 82,
            "y": 241
          }
        ]
      },
      "confidence": 0.9398,
      "id": 24,
      "text": ":nrk1988"
    },
    {
      "boundingBox": {
        "vertices": [
          {
            "x": 10,
            "y": 242
          },
          {
            "x": 118,
            "y": 242
          },
          {
            "x": 118,
            "y": 258
          },
          {
            "x": 10,
            "y": 258
          }
        ]
      },
      "confidence": 0.9484,
      "id": 25,
      "text": "kakaostory2:nrk2"
    },
    {
      "boundingBox": {
        "vertices": [
          {
            "x": 10,
            "y": 259
          },
          {
            "x": 117,
            "y": 259
          },
          {
            "x": 117,
            "y": 274
          },
          {
            "x": 10,
            "y": 274
          }
        ]
      },
      "confidence": 0.9562,
      "id": 26,
      "text": "kakaostory3:nrk1"
    },
    {
      "boundingBox": {
        "vertices": [
          {
            "x": 10,
            "y": 277
          },
          {
            "x": 75,
            "y": 277
          },
          {
            "x": 75,
            "y": 293
          },
          {
            "x": 10,
            "y": 293
          }
        ]
      },
      "confidence": 0.9625,
      "id": 27,
      "text": "instagram:"
    },
    {
      "boundingBox": {
        "vertices": [
          {
            "x": 75,
            "y": 276
          },
          {
            "x": 152,
            "y": 276
          },
          {
            "x": 152,
            "y": 291
          },
          {
            "x": 75,
            "y": 291
          }
        ]
      },
      "confidence": 0.9705,
      "id": 28,
      "text": "nrk.wholesale"
    },
    {
      "boundingBox": {
        "vertices": [
          {
            "x": 10,
            "y": 293
          },
          {
            "x": 171,
            "y": 294
          },
          {
            "x": 171,
            "y": 310
          },
          {
            "x": 10,
            "y": 308
          }
        ]
      },
      "confidence": 0.9864,
      "id": 29,
      "text": "e-mail:nrk1988@naver.com"
    },
    {
      "boundingBox": {
        "vertices": [
          {
            "x": 11,
            "y": 323
          },
          {
            "x": 102,
            "y": 323
          },
          {
            "x": 102,
            "y": 342
          },
          {
            "x": 11,
            "y": 342
          }
        ]
      },
      "confidence": 0.9831,
      "id": 30,
      "text": "24-10-07(월)"
    },
    {
      "boundingBox": {
        "vertices": [
          {
            "x": 136,
            "y": 324
          },
          {
            "x": 207,
            "y": 324
          },
          {
            "x": 207,
            "y": 341
          },
          {
            "x": 136,
            "y": 341
          }
        ]
      },
      "confidence": 0.9817,
      "id": 31,
      "text": "1,194,900"
    },
    {
      "boundingBox": {
        "vertices": [
          {
            "x": 233,
            "y": 323
          },
          {
            "x": 263,
            "y": 323
          },
          {
            "x": 263,
            "y": 340
          },
          {
            "x": 233,
            "y": 340
          }
        ]
      },
      "confidence": 0.9964,
      "id": 32,
      "text": "청구"
    },
    {
      "boundingBox": {
        "vertices": [
          {
            "x": 50,
            "y": 353
          },
          {
            "x": 75,
            "y": 353
          },
          {
            "x": 75,
            "y": 369
          },
          {
            "x": 50,
            "y": 369
          }
        ]
      },
      "confidence": 0.9856,
      "id": 33,
      "text": "품명"
    },
    {
      "boundingBox": {
        "vertices": [
          {
            "x": 144,
            "y": 353
          },
          {
            "x": 171,
            "y": 353
          },
          {
            "x": 171,
            "y": 369
          },
          {
            "x": 144,
            "y": 369
          }
        ]
      },
      "confidence": 0.9871,
      "id": 34,
      "text": "단가"
    },
    {
      "boundingBox": {
        "vertices": [
          {
            "x": 174,
            "y": 353
          },
          {
            "x": 200,
            "y": 353
          },
          {
            "x": 200,
            "y": 368
          },
          {
            "x": 174,
            "y": 368
          }
        ]
      },
      "confidence": 0.9975,
      "id": 35,
      "text": "수량"
    },
    {
      "boundingBox": {
        "vertices": [
          {
            "x": 239,
            "y": 353
          },
          {
            "x": 264,
            "y": 353
          },
          {
            "x": 264,
            "y": 368
          },
          {
            "x": 239,
            "y": 368
          }
        ]
      },
      "confidence": 0.9921,
      "id": 36,
      "text": "금액"
    },
    {
      "boundingBox": {
        "vertices": [
          {
            "x": 10,
            "y": 380
          },
          {
            "x": 148,
            "y": 380
          },
          {
            "x": 148,
            "y": 397
          },
          {
            "x": 10,
            "y": 397
          }
        ]
      },
      "confidence": 0.9593,
      "id": 37,
      "text": "23.ST시보리티/베이지/M"
    },
    {
      "boundingBox": {
        "vertices": [
          {
            "x": 137,
            "y": 399
          },
          {
            "x": 171,
            "y": 399
          },
          {
            "x": 171,
            "y": 414
          },
          {
            "x": 137,
            "y": 414
          }
        ]
      },
      "confidence": 0.9896,
      "id": 38,
      "text": "9,000"
    },
    {
      "boundingBox": {
        "vertices": [
          {
            "x": 191,
            "y": 399
          },
          {
            "x": 199,
            "y": 399
          },
          {
            "x": 199,
            "y": 412
          },
          {
            "x": 191,
            "y": 412
          }
        ]
      },
      "confidence": 0.9808,
      "id": 39,
      "text": "1"
    },
    {
      "boundingBox": {
        "vertices": [
          {
            "x": 232,
            "y": 399
          },
          {
            "x": 266,
            "y": 398
          },
          {
            "x": 266,
            "y": 413
          },
          {
            "x": 233,
            "y": 414
          }
        ]
      },
      "confidence": 0.9854,
      "id": 40,
      "text": "9,000"
    },
    {
      "boundingBox": {
        "vertices": [
          {
            "x": 10,
            "y": 425
          },
          {
            "x": 165,
            "y": 425
          },
          {
            "x": 165,
            "y": 442
          },
          {
            "x": 10,
            "y": 442
          }
        ]
      },
      "confidence": 0.9779,
      "id": 41,
      "text": "※33.골덴팔부바지/베이지/S"
    },
    {
      "boundingBox": {
        "vertices": [
          {
            "x": 132,
            "y": 444
          },
          {
            "x": 171,
            "y": 444
          },
          {
            "x": 171,
            "y": 459
          },
          {
            "x": 132,
            "y": 459
          }
        ]
      },
      "confidence": 0.9894,
      "id": 42,
      "text": "15,000"
    },
    {
      "boundingBox": {
        "vertices": [
          {
            "x": 191,
            "y": 444
          },
          {
            "x": 199,
            "y": 444
          },
          {
            "x": 199,
            "y": 457
          },
          {
            "x": 191,
            "y": 457
          }
        ]
      },
      "confidence": 0.9792,
      "id": 43,
      "text": "1"
    },
    {
      "boundingBox": {
        "vertices": [
          {
            "x": 227,
            "y": 444
          },
          {
            "x": 266,
            "y": 444
          },
          {
            "x": 266,
            "y": 459
          },
          {
            "x": 227,
            "y": 459
          }
        ]
      },
      "confidence": 0.9885,
      "id": 44,
      "text": "15,000"
    },
    {
      "boundingBox": {
        "vertices": [
          {
            "x": 159,
            "y": 457
          },
          {
            "x": 237,
            "y": 457
          },
          {
            "x": 237,
            "y": 469
          },
          {
            "x": 159,
            "y": 469
          }
        ]
      },
      "confidence": 0.9856,
      "id": 45,
      "text": "-------------"
    },
    {
      "boundingBox": {
        "vertices": [
          {
            "x": 11,
            "y": 471
          },
          {
            "x": 149,
            "y": 471
          },
          {
            "x": 149,
            "y": 487
          },
          {
            "x": 11,
            "y": 487
          }
        ]
      },
      "confidence": 0.9107,
      "id": 46,
      "text": "33.골덴팔부바지/차콜/XL"
    },
    {
      "boundingBox": {
        "vertices": [
          {
            "x": 132,
            "y": 489
          },
          {
            "x": 171,
            "y": 489
          },
          {
            "x": 171,
            "y": 504
          },
          {
            "x": 132,
            "y": 504
          }
        ]
      },
      "confidence": 0.9926,
      "id": 47,
      "text": "15,000"
    },
    {
      "boundingBox": {
        "vertices": [
          {
            "x": 191,
            "y": 489
          },
          {
            "x": 199,
            "y": 489
          },
          {
            "x": 199,
            "y": 502
          },
          {
            "x": 191,
            "y": 502
          }
        ]
      },
      "confidence": 0.9631,
      "id": 48,
      "text": "1"
    },
    {
      "boundingBox": {
        "vertices": [
          {
            "x": 227,
            "y": 489
          },
          {
            "x": 266,
            "y": 489
          },
          {
            "x": 266,
            "y": 504
          },
          {
            "x": 227,
            "y": 504
          }
        ]
      },
      "confidence": 0.9927,
      "id": 49,
      "text": "15,000"
    },
    {
      "boundingBox": {
        "vertices": [
          {
            "x": 11,
            "y": 515
          },
          {
            "x": 168,
            "y": 515
          },
          {
            "x": 168,
            "y": 532
          },
          {
            "x": 11,
            "y": 532
          }
        ]
      },
      "confidence": 0.9878,
      "id": 50,
      "text": "5.그라운드남방/아이보리/XL"
    },
    {
      "boundingBox": {
        "vertices": [
          {
            "x": 132,
            "y": 533
          },
          {
            "x": 171,
            "y": 533
          },
          {
            "x": 171,
            "y": 549
          },
          {
            "x": 132,
            "y": 549
          }
        ]
      },
      "confidence": 0.9899,
      "id": 51,
      "text": "18,000"
    },
    {
      "boundingBox": {
        "vertices": [
          {
            "x": 191,
            "y": 534
          },
          {
            "x": 199,
            "y": 534
          },
          {
            "x": 199,
            "y": 547
          },
          {
            "x": 191,
            "y": 547
          }
        ]
      },
      "confidence": 0.9413,
      "id": 52,
      "text": "1"
    },
    {
      "boundingBox": {
        "vertices": [
          {
            "x": 227,
            "y": 533
          },
          {
            "x": 266,
            "y": 533
          },
          {
            "x": 266,
            "y": 548
          },
          {
            "x": 227,
            "y": 548
          }
        ]
      },
      "confidence": 0.9857,
      "id": 53,
      "text": "18,000"
    },
    {
      "boundingBox": {
        "vertices": [
          {
            "x": 10,
            "y": 560
          },
          {
            "x": 168,
            "y": 560
          },
          {
            "x": 168,
            "y": 577
          },
          {
            "x": 10,
            "y": 577
          }
        ]
      },
      "confidence": 0.891,
      "id": 54,
      "text": "20.덴깡카라맨투맨/검정/4XL"
    },
    {
      "boundingBox": {
        "vertices": [
          {
            "x": 131,
            "y": 579
          },
          {
            "x": 171,
            "y": 579
          },
          {
            "x": 171,
            "y": 594
          },
          {
            "x": 131,
            "y": 594
          }
        ]
      },
      "confidence": 0.9937,
      "id": 55,
      "text": "21,000"
    },
    {
      "boundingBox": {
        "vertices": [
          {
            "x": 191,
            "y": 580
          },
          {
            "x": 199,
            "y": 580
          },
          {
            "x": 199,
            "y": 592
          },
          {
            "x": 191,
            "y": 592
          }
        ]
      },
      "confidence": 0.9635,
      "id": 56,
      "text": "1"
    },
    {
      "boundingBox": {
        "vertices": [
          {
            "x": 226,
            "y": 578
          },
          {
            "x": 265,
            "y": 578
          },
          {
            "x": 265,
            "y": 594
          },
          {
            "x": 226,
            "y": 594
          }
        ]
      },
      "confidence": 0.9899,
      "id": 57,
      "text": "21,000"
    },
    {
      "boundingBox": {
        "vertices": [
          {
            "x": 171,
            "y": 593
          },
          {
            "x": 231,
            "y": 591
          },
          {
            "x": 231,
            "y": 602
          },
          {
            "x": 172,
            "y": 603
          }
        ]
      },
      "confidence": 0.9973,
      "id": 58,
      "text": "----------"
    },
    {
      "boundingBox": {
        "vertices": [
          {
            "x": 10,
            "y": 606
          },
          {
            "x": 165,
            "y": 606
          },
          {
            "x": 165,
            "y": 622
          },
          {
            "x": 10,
            "y": 622
          }
        ]
      },
      "confidence": 0.8896,
      "id": 59,
      "text": "※20.덴장카라맨투맨/핑크/S"
    },
    {
      "boundingBox": {
        "vertices": [
          {
            "x": 132,
            "y": 624
          },
          {
            "x": 171,
            "y": 624
          },
          {
            "x": 171,
            "y": 639
          },
          {
            "x": 132,
            "y": 639
          }
        ]
      },
      "confidence": 0.9902,
      "id": 60,
      "text": "18,000"
    },
    {
      "boundingBox": {
        "vertices": [
          {
            "x": 191,
            "y": 625
          },
          {
            "x": 199,
            "y": 625
          },
          {
            "x": 199,
            "y": 637
          },
          {
            "x": 191,
            "y": 637
          }
        ]
      },
      "confidence": 0.9812,
      "id": 61,
      "text": "1"
    },
    {
      "boundingBox": {
        "vertices": [
          {
            "x": 227,
            "y": 624
          },
          {
            "x": 265,
            "y": 624
          },
          {
            "x": 265,
            "y": 638
          },
          {
            "x": 227,
            "y": 638
          }
        ]
      },
      "confidence": 0.9905,
      "id": 62,
      "text": "18,000"
    },
    {
      "boundingBox": {
        "vertices": [
          {
            "x": 178,
            "y": 636
          },
          {
            "x": 266,
            "y": 636
          },
          {
            "x": 266,
            "y": 648
          },
          {
            "x": 178,
            "y": 648
          }
        ]
      },
      "confidence": 0.9817,
      "id": 63,
      "text": "---------------"
    },
    {
      "boundingBox": {
        "vertices": [
          {
            "x": 10,
            "y": 651
          },
          {
            "x": 168,
            "y": 650
          },
          {
            "x": 168,
            "y": 667
          },
          {
            "x": 10,
            "y": 668
          }
        ]
      },
      "confidence": 0.842,
      "id": 64,
      "text": "※20.덴깡카라맨투맨/핑크/M"
    },
    {
      "boundingBox": {
        "vertices": [
          {
            "x": 132,
            "y": 669
          },
          {
            "x": 171,
            "y": 669
          },
          {
            "x": 171,
            "y": 684
          },
          {
            "x": 132,
            "y": 684
          }
        ]
      },
      "confidence": 0.989,
      "id": 65,
      "text": "18,000"
    },
    {
      "boundingBox": {
        "vertices": [
          {
            "x": 191,
            "y": 670
          },
          {
            "x": 199,
            "y": 670
          },
          {
            "x": 199,
            "y": 682
          },
          {
            "x": 191,
            "y": 682
          }
        ]
      },
      "confidence": 0.9466,
      "id": 66,
      "text": "1"
    },
    {
      "boundingBox": {
        "vertices": [
          {
            "x": 227,
            "y": 669
          },
          {
            "x": 265,
            "y": 669
          },
          {
            "x": 265,
            "y": 683
          },
          {
            "x": 227,
            "y": 683
          }
        ]
      },
      "confidence": 0.9885,
      "id": 67,
      "text": "18,000"
    },
    {
      "boundingBox": {
        "vertices": [
          {
            "x": 11,
            "y": 695
          },
          {
            "x": 123,
            "y": 695
          },
          {
            "x": 123,
            "y": 712
          },
          {
            "x": 11,
            "y": 712
          }
        ]
      },
      "confidence": 0.98,
      "id": 68,
      "text": "8.면카라니트/검정/L"
    },
    {
      "boundingBox": {
        "vertices": [
          {
            "x": 131,
            "y": 714
          },
          {
            "x": 171,
            "y": 714
          },
          {
            "x": 171,
            "y": 728
          },
          {
            "x": 131,
            "y": 728
          }
        ]
      },
      "confidence": 0.9941,
      "id": 69,
      "text": "22,000"
    },
    {
      "boundingBox": {
        "vertices": [
          {
            "x": 190,
            "y": 715
          },
          {
            "x": 200,
            "y": 715
          },
          {
            "x": 200,
            "y": 727
          },
          {
            "x": 190,
            "y": 727
          }
        ]
      },
      "confidence": 0.9778,
      "id": 70,
      "text": "2"
    },
    {
      "boundingBox": {
        "vertices": [
          {
            "x": 226,
            "y": 714
          },
          {
            "x": 266,
            "y": 714
          },
          {
            "x": 266,
            "y": 728
          },
          {
            "x": 226,
            "y": 728
          }
        ]
      },
      "confidence": 0.9921,
      "id": 71,
      "text": "44,000"
    },
    {
      "boundingBox": {
        "vertices": [
          {
            "x": 11,
            "y": 741
          },
          {
            "x": 154,
            "y": 741
          },
          {
            "x": 154,
            "y": 757
          },
          {
            "x": 11,
            "y": 757
          }
        ]
      },
      "confidence": 0.9758,
      "id": 72,
      "text": "15.버디단가라세트/레드/L"
    },
    {
      "boundingBox": {
        "vertices": [
          {
            "x": 131,
            "y": 759
          },
          {
            "x": 171,
            "y": 759
          },
          {
            "x": 171,
            "y": 773
          },
          {
            "x": 131,
            "y": 773
          }
        ]
      },
      "confidence": 0.9932,
      "id": 73,
      "text": "23,000"
    },
    {
      "boundingBox": {
        "vertices": [
          {
            "x": 191,
            "y": 760
          },
          {
            "x": 199,
            "y": 760
          },
          {
            "x": 199,
            "y": 772
          },
          {
            "x": 191,
            "y": 772
          }
        ]
      },
      "confidence": 0.9637,
      "id": 74,
      "text": "1"
    },
    {
      "boundingBox": {
        "vertices": [
          {
            "x": 226,
            "y": 759
          },
          {
            "x": 266,
            "y": 759
          },
          {
            "x": 266,
            "y": 773
          },
          {
            "x": 226,
            "y": 773
          }
        ]
      },
      "confidence": 0.9946,
      "id": 75,
      "text": "23,000"
    },
    {
      "boundingBox": {
        "vertices": [
          {
            "x": 177,
            "y": 775
          },
          {
            "x": 231,
            "y": 771
          },
          {
            "x": 231,
            "y": 781
          },
          {
            "x": 178,
            "y": 784
          }
        ]
      },
      "confidence": 0.9977,
      "id": 76,
      "text": "---------"
    },
    {
      "boundingBox": {
        "vertices": [
          {
            "x": 11,
            "y": 786
          },
          {
            "x": 163,
            "y": 785
          },
          {
            "x": 163,
            "y": 802
          },
          {
            "x": 11,
            "y": 802
          }
        ]
      },
      "confidence": 0.9826,
      "id": 77,
      "text": "※15.버디단가라세트/파랑/L"
    },
    {
      "boundingBox": {
        "vertices": [
          {
            "x": 131,
            "y": 804
          },
          {
            "x": 171,
            "y": 804
          },
          {
            "x": 171,
            "y": 818
          },
          {
            "x": 131,
            "y": 818
          }
        ]
      },
      "confidence": 0.9873,
      "id": 78,
      "text": "23,000"
    },
    {
      "boundingBox": {
        "vertices": [
          {
            "x": 191,
            "y": 805
          },
          {
            "x": 199,
            "y": 805
          },
          {
            "x": 199,
            "y": 817
          },
          {
            "x": 191,
            "y": 817
          }
        ]
      },
      "confidence": 0.9494,
      "id": 79,
      "text": "1"
    },
    {
      "boundingBox": {
        "vertices": [
          {
            "x": 226,
            "y": 804
          },
          {
            "x": 266,
            "y": 804
          },
          {
            "x": 266,
            "y": 818
          },
          {
            "x": 226,
            "y": 818
          }
        ]
      },
      "confidence": 0.9881,
      "id": 80,
      "text": "23,000"
    },
    {
      "boundingBox": {
        "vertices": [
          {
            "x": 11,
            "y": 830
          },
          {
            "x": 119,
            "y": 830
          },
          {
            "x": 119,
            "y": 847
          },
          {
            "x": 11,
            "y": 847
          }
        ]
      },
      "confidence": 0.9326,
      "id": 81,
      "text": "25.보데티/네이비/S"
    },
    {
      "boundingBox": {
        "vertices": [
          {
            "x": 132,
            "y": 849
          },
          {
            "x": 171,
            "y": 849
          },
          {
            "x": 171,
            "y": 863
          },
          {
            "x": 132,
            "y": 863
          }
        ]
      },
      "confidence": 0.9922,
      "id": 82,
      "text": "10,000"
    },
    {
      "boundingBox": {
        "vertices": [
          {
            "x": 191,
            "y": 849
          },
          {
            "x": 199,
            "y": 849
          },
          {
            "x": 199,
            "y": 862
          },
          {
            "x": 191,
            "y": 862
          }
        ]
      },
      "confidence": 0.9855,
      "id": 83,
      "text": "1"
    },
    {
      "boundingBox": {
        "vertices": [
          {
            "x": 227,
            "y": 849
          },
          {
            "x": 266,
            "y": 849
          },
          {
            "x": 266,
            "y": 863
          },
          {
            "x": 227,
            "y": 863
          }
        ]
      },
      "confidence": 0.9917,
      "id": 84,
      "text": "10,000"
    },
    {
      "boundingBox": {
        "vertices": [
          {
            "x": 195,
            "y": 863
          },
          {
            "x": 226,
            "y": 863
          },
          {
            "x": 226,
            "y": 871
          },
          {
            "x": 195,
            "y": 871
          }
        ]
      },
      "confidence": 0.9985,
      "id": 85,
      "text": "-----"
    },
    {
      "boundingBox": {
        "vertices": [
          {
            "x": 11,
            "y": 875
          },
          {
            "x": 107,
            "y": 875
          },
          {
            "x": 107,
            "y": 891
          },
          {
            "x": 11,
            "y": 891
          }
        ]
      },
      "confidence": 0.9567,
      "id": 86,
      "text": "25.보데티/아이/S"
    },
    {
      "boundingBox": {
        "vertices": [
          {
            "x": 132,
            "y": 893
          },
          {
            "x": 171,
            "y": 893
          },
          {
            "x": 171,
            "y": 907
          },
          {
            "x": 132,
            "y": 907
          }
        ]
      },
      "confidence": 0.9874,
      "id": 87,
      "text": "10,000"
    },
    {
      "boundingBox": {
        "vertices": [
          {
            "x": 191,
            "y": 894
          },
          {
            "x": 199,
            "y": 894
          },
          {
            "x": 199,
            "y": 906
          },
          {
            "x": 191,
            "y": 906
          }
        ]
      },
      "confidence": 0.9466,
      "id": 88,
      "text": "1"
    },
    {
      "boundingBox": {
        "vertices": [
          {
            "x": 227,
            "y": 893
          },
          {
            "x": 265,
            "y": 893
          },
          {
            "x": 265,
            "y": 907
          },
          {
            "x": 227,
            "y": 907
          }
        ]
      },
      "confidence": 0.9874,
      "id": 89,
      "text": "10,000"
    },
    {
      "boundingBox": {
        "vertices": [
          {
            "x": 11,
            "y": 920
          },
          {
            "x": 130,
            "y": 920
          },
          {
            "x": 130,
            "y": 936
          },
          {
            "x": 11,
            "y": 936
          }
        ]
      },
      "confidence": 0.9514,
      "id": 90,
      "text": "9.스쿨룩조끼/아이/XS"
    },
    {
      "boundingBox": {
        "vertices": [
          {
            "x": 132,
            "y": 938
          },
          {
            "x": 171,
            "y": 938
          },
          {
            "x": 171,
            "y": 952
          },
          {
            "x": 132,
            "y": 952
          }
        ]
      },
      "confidence": 0.9895,
      "id": 91,
      "text": "18,000"
    },
    {
      "boundingBox": {
        "vertices": [
          {
            "x": 191,
            "y": 939
          },
          {
            "x": 199,
            "y": 939
          },
          {
            "x": 199,
            "y": 951
          },
          {
            "x": 191,
            "y": 951
          }
        ]
      },
      "confidence": 0.9858,
      "id": 92,
      "text": "1"
    },
    {
      "boundingBox": {
        "vertices": [
          {
            "x": 227,
            "y": 938
          },
          {
            "x": 266,
            "y": 938
          },
          {
            "x": 266,
            "y": 952
          },
          {
            "x": 227,
            "y": 952
          }
        ]
      },
      "confidence": 0.9913,
      "id": 93,
      "text": "18,000"
    },
    {
      "boundingBox": {
        "vertices": [
          {
            "x": 171,
            "y": 952
          },
          {
            "x": 232,
            "y": 952
          },
          {
            "x": 232,
            "y": 962
          },
          {
            "x": 171,
            "y": 962
          }
        ]
      },
      "confidence": 0.9881,
      "id": 94,
      "text": "----------"
    },
    {
      "boundingBox": {
        "vertices": [
          {
            "x": 11,
            "y": 965
          },
          {
            "x": 138,
            "y": 965
          },
          {
            "x": 138,
            "y": 982
          },
          {
            "x": 11,
            "y": 982
          }
        ]
      },
      "confidence": 0.9811,
      "id": 95,
      "text": "9.스쿨룩조끼/아이/4XL"
    },
    {
      "boundingBox": {
        "vertices": [
          {
            "x": 131,
            "y": 983
          },
          {
            "x": 171,
            "y": 983
          },
          {
            "x": 171,
            "y": 997
          },
          {
            "x": 131,
            "y": 997
          }
        ]
      },
      "confidence": 0.9918,
      "id": 96,
      "text": "21,000"
    },
    {
      "boundingBox": {
        "vertices": [
          {
            "x": 191,
            "y": 983
          },
          {
            "x": 199,
            "y": 983
          },
          {
            "x": 199,
            "y": 996
          },
          {
            "x": 191,
            "y": 996
          }
        ]
      },
      "confidence": 0.9238,
      "id": 97,
      "text": "1"
    },
    {
      "boundingBox": {
        "vertices": [
          {
            "x": 226,
            "y": 983
          },
          {
            "x": 265,
            "y": 983
          },
          {
            "x": 265,
            "y": 997
          },
          {
            "x": 226,
            "y": 997
          }
        ]
      },
      "confidence": 0.992,
      "id": 98,
      "text": "21,000"
    },
    {
      "boundingBox": {
        "vertices": [
          {
            "x": 10,
            "y": 1010
          },
          {
            "x": 180,
            "y": 1010
          },
          {
            "x": 180,
            "y": 1026
          },
          {
            "x": 10,
            "y": 1026
          }
        ]
      },
      "confidence": 0.9519,
      "id": 99,
      "text": "※14.어텀테이프세트/메란지/M"
    },
    {
      "boundingBox": {
        "vertices": [
          {
            "x": 131,
            "y": 1028
          },
          {
            "x": 171,
            "y": 1028
          },
          {
            "x": 171,
            "y": 1042
          },
          {
            "x": 131,
            "y": 1042
          }
        ]
      },
      "confidence": 0.9901,
      "id": 100,
      "text": "25,000"
    },
    {
      "boundingBox": {
        "vertices": [
          {
            "x": 191,
            "y": 1029
          },
          {
            "x": 199,
            "y": 1029
          },
          {
            "x": 199,
            "y": 1041
          },
          {
            "x": 191,
            "y": 1041
          }
        ]
      },
      "confidence": 0.9494,
      "id": 101,
      "text": "1"
    },
    {
      "boundingBox": {
        "vertices": [
          {
            "x": 226,
            "y": 1028
          },
          {
            "x": 266,
            "y": 1028
          },
          {
            "x": 266,
            "y": 1042
          },
          {
            "x": 226,
            "y": 1042
          }
        ]
      },
      "confidence": 0.9897,
      "id": 102,
      "text": "25,000"
    },
    {
      "boundingBox": {
        "vertices": [
          {
            "x": 183,
            "y": 1042
          },
          {
            "x": 231,
            "y": 1042
          },
          {
            "x": 231,
            "y": 1052
          },
          {
            "x": 183,
            "y": 1052
          }
        ]
      },
      "confidence": 0.9979,
      "id": 103,
      "text": "--------"
    },
    {
      "boundingBox": {
        "vertices": [
          {
            "x": 10,
            "y": 1055
          },
          {
            "x": 183,
            "y": 1054
          },
          {
            "x": 183,
            "y": 1070
          },
          {
            "x": 10,
            "y": 1071
          }
        ]
      },
      "confidence": 0.9655,
      "id": 104,
      "text": "※14.어텀테이프세트/메란지/XL"
    },
    {
      "boundingBox": {
        "vertices": [
          {
            "x": 131,
            "y": 1073
          },
          {
            "x": 171,
            "y": 1073
          },
          {
            "x": 171,
            "y": 1087
          },
          {
            "x": 131,
            "y": 1087
          }
        ]
      },
      "confidence": 0.994,
      "id": 105,
      "text": "25,000"
    },
    {
      "boundingBox": {
        "vertices": [
          {
            "x": 191,
            "y": 1074
          },
          {
            "x": 199,
            "y": 1074
          },
          {
            "x": 199,
            "y": 1086
          },
          {
            "x": 191,
            "y": 1086
          }
        ]
      },
      "confidence": 0.9832,
      "id": 106,
      "text": "1"
    },
    {
      "boundingBox": {
        "vertices": [
          {
            "x": 226,
            "y": 1073
          },
          {
            "x": 266,
            "y": 1073
          },
          {
            "x": 266,
            "y": 1087
          },
          {
            "x": 226,
            "y": 1087
          }
        ]
      },
      "confidence": 0.9929,
      "id": 107,
      "text": "25,000"
    },
    {
      "boundingBox": {
        "vertices": [
          {
            "x": 10,
            "y": 1100
          },
          {
            "x": 131,
            "y": 1099
          },
          {
            "x": 131,
            "y": 1115
          },
          {
            "x": 10,
            "y": 1116
          }
        ]
      },
      "confidence": 0.8847,
      "id": 108,
      "text": "21.와플테입티/곤색/S"
    },
    {
      "boundingBox": {
        "vertices": [
          {
            "x": 132,
            "y": 1118
          },
          {
            "x": 171,
            "y": 1118
          },
          {
            "x": 171,
            "y": 1132
          },
          {
            "x": 132,
            "y": 1132
          }
        ]
      },
      "confidence": 0.9899,
      "id": 109,
      "text": "16,000"
    },
    {
      "boundingBox": {
        "vertices": [
          {
            "x": 191,
            "y": 1118
          },
          {
            "x": 199,
            "y": 1118
          },
          {
            "x": 199,
            "y": 1131
          },
          {
            "x": 191,
            "y": 1131
          }
        ]
      },
      "confidence": 0.9588,
      "id": 110,
      "text": "1"
    },
    {
      "boundingBox": {
        "vertices": [
          {
            "x": 227,
            "y": 1118
          },
          {
            "x": 266,
            "y": 1118
          },
          {
            "x": 266,
            "y": 1132
          },
          {
            "x": 227,
            "y": 1132
          }
        ]
      },
      "confidence": 0.9906,
      "id": 111,
      "text": "16,000"
    },
    {
      "boundingBox": {
        "vertices": [
          {
            "x": 11,
            "y": 1144
          },
          {
            "x": 155,
            "y": 1144
          },
          {
            "x": 155,
            "y": 1160
          },
          {
            "x": 11,
            "y": 1160
          }
        ]
      },
      "confidence": 0.981,
      "id": 112,
      "text": "32.주름팔부바지/메란지/S"
    },
    {
      "boundingBox": {
        "vertices": [
          {
            "x": 132,
            "y": 1163
          },
          {
            "x": 171,
            "y": 1163
          },
          {
            "x": 171,
            "y": 1178
          },
          {
            "x": 132,
            "y": 1178
          }
        ]
      },
      "confidence": 0.9932,
      "id": 113,
      "text": "17,000"
    },
    {
      "boundingBox": {
        "vertices": [
          {
            "x": 191,
            "y": 1163
          },
          {
            "x": 199,
            "y": 1163
          },
          {
            "x": 199,
            "y": 1176
          },
          {
            "x": 191,
            "y": 1176
          }
        ]
      },
      "confidence": 0.9716,
      "id": 114,
      "text": "1"
    },
    {
      "boundingBox": {
        "vertices": [
          {
            "x": 227,
            "y": 1163
          },
          {
            "x": 265,
            "y": 1163
          },
          {
            "x": 265,
            "y": 1177
          },
          {
            "x": 227,
            "y": 1177
          }
        ]
      },
      "confidence": 0.9942,
      "id": 115,
      "text": "17,000"
    },
    {
      "boundingBox": {
        "vertices": [
          {
            "x": 165,
            "y": 1178
          },
          {
            "x": 231,
            "y": 1174
          },
          {
            "x": 232,
            "y": 1187
          },
          {
            "x": 166,
            "y": 1190
          }
        ]
      },
      "confidence": 0.9955,
      "id": 116,
      "text": "-----------"
    },
    {
      "boundingBox": {
        "vertices": [
          {
            "x": 11,
            "y": 1190
          },
          {
            "x": 159,
            "y": 1190
          },
          {
            "x": 159,
            "y": 1206
          },
          {
            "x": 11,
            "y": 1206
          }
        ]
      },
      "confidence": 0.984,
      "id": 117,
      "text": "32.주름팔부바지/메란지/M"
    },
    {
      "boundingBox": {
        "vertices": [
          {
            "x": 132,
            "y": 1208
          },
          {
            "x": 171,
            "y": 1208
          },
          {
            "x": 171,
            "y": 1223
          },
          {
            "x": 132,
            "y": 1223
          }
        ]
      },
      "confidence": 0.9941,
      "id": 118,
      "text": "17,000"
    },
    {
      "boundingBox": {
        "vertices": [
          {
            "x": 191,
            "y": 1208
          },
          {
            "x": 199,
            "y": 1208
          },
          {
            "x": 199,
            "y": 1221
          },
          {
            "x": 191,
            "y": 1221
          }
        ]
      },
      "confidence": 0.9542,
      "id": 119,
      "text": "1"
    },
    {
      "boundingBox": {
        "vertices": [
          {
            "x": 227,
            "y": 1208
          },
          {
            "x": 265,
            "y": 1208
          },
          {
            "x": 265,
            "y": 1222
          },
          {
            "x": 227,
            "y": 1222
          }
        ]
      },
      "confidence": 0.9943,
      "id": 120,
      "text": "17,000"
    },
    {
      "boundingBox": {
        "vertices": [
          {
            "x": 10,
            "y": 1234
          },
          {
            "x": 159,
            "y": 1234
          },
          {
            "x": 159,
            "y": 1251
          },
          {
            "x": 10,
            "y": 1251
          }
        ]
      },
      "confidence": 0.9698,
      "id": 121,
      "text": "26.트렌디시보리티/와인/M"
    },
    {
      "boundingBox": {
        "vertices": [
          {
            "x": 132,
            "y": 1253
          },
          {
            "x": 171,
            "y": 1253
          },
          {
            "x": 171,
            "y": 1268
          },
          {
            "x": 132,
            "y": 1268
          }
        ]
      },
      "confidence": 0.99,
      "id": 122,
      "text": "12,000"
    },
    {
      "boundingBox": {
        "vertices": [
          {
            "x": 191,
            "y": 1253
          },
          {
            "x": 199,
            "y": 1253
          },
          {
            "x": 199,
            "y": 1265
          },
          {
            "x": 191,
            "y": 1265
          }
        ]
      },
      "confidence": 0.9469,
      "id": 123,
      "text": "1"
    },
    {
      "boundingBox": {
        "vertices": [
          {
            "x": 227,
            "y": 1253
          },
          {
            "x": 266,
            "y": 1252
          },
          {
            "x": 266,
            "y": 1267
          },
          {
            "x": 227,
            "y": 1268
          }
        ]
      },
      "confidence": 0.9863,
      "id": 124,
      "text": "12,000"
    },
    {
      "boundingBox": {
        "vertices": [
          {
            "x": 11,
            "y": 1280
          },
          {
            "x": 179,
            "y": 1280
          },
          {
            "x": 179,
            "y": 1296
          },
          {
            "x": 11,
            "y": 1296
          }
        ]
      },
      "confidence": 0.9841,
      "id": 125,
      "text": "16.파리카라세트/백메란지/4XL"
    },
    {
      "boundingBox": {
        "vertices": [
          {
            "x": 131,
            "y": 1298
          },
          {
            "x": 171,
            "y": 1298
          },
          {
            "x": 171,
            "y": 1313
          },
          {
            "x": 131,
            "y": 1313
          }
        ]
      },
      "confidence": 0.9926,
      "id": 126,
      "text": "26,000"
    },
    {
      "boundingBox": {
        "vertices": [
          {
            "x": 191,
            "y": 1299
          },
          {
            "x": 199,
            "y": 1299
          },
          {
            "x": 199,
            "y": 1311
          },
          {
            "x": 191,
            "y": 1311
          }
        ]
      },
      "confidence": 0.977,
      "id": 127,
      "text": "1"
    },
    {
      "boundingBox": {
        "vertices": [
          {
            "x": 226,
            "y": 1297
          },
          {
            "x": 265,
            "y": 1298
          },
          {
            "x": 265,
            "y": 1313
          },
          {
            "x": 226,
            "y": 1312
          }
        ]
      },
      "confidence": 0.993,
      "id": 128,
      "text": "26,000"
    },
    {
      "boundingBox": {
        "vertices": [
          {
            "x": 10,
            "y": 1324
          },
          {
            "x": 171,
            "y": 1324
          },
          {
            "x": 171,
            "y": 1341
          },
          {
            "x": 10,
            "y": 1341
          }
        ]
      },
      "confidence": 0.9826,
      "id": 129,
      "text": "※12.팔팔상하세트/네이비/XL"
    },
    {
      "boundingBox": {
        "vertices": [
          {
            "x": 131,
            "y": 1343
          },
          {
            "x": 171,
            "y": 1343
          },
          {
            "x": 171,
            "y": 1357
          },
          {
            "x": 131,
            "y": 1357
          }
        ]
      },
      "confidence": 0.9934,
      "id": 130,
      "text": "22,000"
    },
    {
      "boundingBox": {
        "vertices": [
          {
            "x": 191,
            "y": 1344
          },
          {
            "x": 199,
            "y": 1344
          },
          {
            "x": 199,
            "y": 1355
          },
          {
            "x": 190,
            "y": 1355
          }
        ]
      },
      "confidence": 0.9808,
      "id": 131,
      "text": "1"
    },
    {
      "boundingBox": {
        "vertices": [
          {
            "x": 226,
            "y": 1342
          },
          {
            "x": 265,
            "y": 1342
          },
          {
            "x": 265,
            "y": 1357
          },
          {
            "x": 226,
            "y": 1357
          }
        ]
      },
      "confidence": 0.9939,
      "id": 132,
      "text": "22,000"
    },
    {
      "boundingBox": {
        "vertices": [
          {
            "x": 165,
            "y": 1356
          },
          {
            "x": 266,
            "y": 1356
          },
          {
            "x": 266,
            "y": 1367
          },
          {
            "x": 165,
            "y": 1367
          }
        ]
      },
      "confidence": 0.9627,
      "id": 133,
      "text": "-----------------"
    },
    {
      "boundingBox": {
        "vertices": [
          {
            "x": 12,
            "y": 1370
          },
          {
            "x": 156,
            "y": 1370
          },
          {
            "x": 156,
            "y": 1386
          },
          {
            "x": 12,
            "y": 1386
          }
        ]
      },
      "confidence": 0.9867,
      "id": 134,
      "text": "12.팔팔상하세트/크림/2XL"
    },
    {
      "boundingBox": {
        "vertices": [
          {
            "x": 131,
            "y": 1387
          },
          {
            "x": 171,
            "y": 1387
          },
          {
            "x": 171,
            "y": 1403
          },
          {
            "x": 131,
            "y": 1403
          }
        ]
      },
      "confidence": 0.9938,
      "id": 135,
      "text": "25,000"
    },
    {
      "boundingBox": {
        "vertices": [
          {
            "x": 190,
            "y": 1389
          },
          {
            "x": 199,
            "y": 1389
          },
          {
            "x": 199,
            "y": 1400
          },
          {
            "x": 191,
            "y": 1400
          }
        ]
      },
      "confidence": 0.9832,
      "id": 136,
      "text": "1"
    },
    {
      "boundingBox": {
        "vertices": [
          {
            "x": 226,
            "y": 1388
          },
          {
            "x": 266,
            "y": 1388
          },
          {
            "x": 266,
            "y": 1402
          },
          {
            "x": 226,
            "y": 1402
          }
        ]
      },
      "confidence": 0.9937,
      "id": 137,
      "text": "25,000"
    },
    {
      "boundingBox": {
        "vertices": [
          {
            "x": 171,
            "y": 1401
          },
          {
            "x": 219,
            "y": 1401
          },
          {
            "x": 219,
            "y": 1411
          },
          {
            "x": 171,
            "y": 1411
          }
        ]
      },
      "confidence": 0.9946,
      "id": 138,
      "text": "--------"
    },
    {
      "boundingBox": {
        "vertices": [
          {
            "x": 11,
            "y": 1415
          },
          {
            "x": 142,
            "y": 1415
          },
          {
            "x": 142,
            "y": 1431
          },
          {
            "x": 11,
            "y": 1431
          }
        ]
      },
      "confidence": 0.9863,
      "id": 139,
      "text": "12.팔팔상하세트/크림/L"
    },
    {
      "boundingBox": {
        "vertices": [
          {
            "x": 131,
            "y": 1432
          },
          {
            "x": 171,
            "y": 1432
          },
          {
            "x": 171,
            "y": 1448
          },
          {
            "x": 131,
            "y": 1448
          }
        ]
      },
      "confidence": 0.9944,
      "id": 140,
      "text": "22,000"
    },
    {
      "boundingBox": {
        "vertices": [
          {
            "x": 191,
            "y": 1433
          },
          {
            "x": 199,
            "y": 1433
          },
          {
            "x": 199,
            "y": 1447
          },
          {
            "x": 191,
            "y": 1447
          }
        ]
      },
      "confidence": 0.9631,
      "id": 141,
      "text": "1"
    },
    {
      "boundingBox": {
        "vertices": [
          {
            "x": 226,
            "y": 1432
          },
          {
            "x": 266,
            "y": 1433
          },
          {
            "x": 266,
            "y": 1448
          },
          {
            "x": 226,
            "y": 1447
          }
        ]
      },
      "confidence": 0.994,
      "id": 142,
      "text": "22,000"
    },
    {
      "boundingBox": {
        "vertices": [
          {
            "x": 195,
            "y": 1444
          },
          {
            "x": 231,
            "y": 1444
          },
          {
            "x": 231,
            "y": 1455
          },
          {
            "x": 195,
            "y": 1455
          }
        ]
      },
      "confidence": 0.9976,
      "id": 143,
      "text": "------"
    },
    {
      "boundingBox": {
        "vertices": [
          {
            "x": 11,
            "y": 1460
          },
          {
            "x": 152,
            "y": 1460
          },
          {
            "x": 152,
            "y": 1476
          },
          {
            "x": 11,
            "y": 1476
          }
        ]
      },
      "confidence": 0.9808,
      "id": 144,
      "text": "※12팔팔상하세트/크림/S"
    },
    {
      "boundingBox": {
        "vertices": [
          {
            "x": 131,
            "y": 1478
          },
          {
            "x": 171,
            "y": 1478
          },
          {
            "x": 171,
            "y": 1492
          },
          {
            "x": 131,
            "y": 1492
          }
        ]
      },
      "confidence": 0.9938,
      "id": 145,
      "text": "22,000"
    },
    {
      "boundingBox": {
        "vertices": [
          {
            "x": 191,
            "y": 1479
          },
          {
            "x": 199,
            "y": 1479
          },
          {
            "x": 199,
            "y": 1491
          },
          {
            "x": 191,
            "y": 1491
          }
        ]
      },
      "confidence": 0.9577,
      "id": 146,
      "text": "1"
    },
    {
      "boundingBox": {
        "vertices": [
          {
            "x": 226,
            "y": 1478
          },
          {
            "x": 266,
            "y": 1478
          },
          {
            "x": 266,
            "y": 1492
          },
          {
            "x": 226,
            "y": 1492
          }
        ]
      },
      "confidence": 0.9952,
      "id": 147,
      "text": "22,000"
    },
    {
      "boundingBox": {
        "vertices": [
          {
            "x": 11,
            "y": 1504
          },
          {
            "x": 135,
            "y": 1504
          },
          {
            "x": 135,
            "y": 1521
          },
          {
            "x": 11,
            "y": 1521
          }
        ]
      },
      "confidence": 0.9838,
      "id": 148,
      "text": "7.피셔맨니트/네이비/L"
    },
    {
      "boundingBox": {
        "vertices": [
          {
            "x": 131,
            "y": 1523
          },
          {
            "x": 171,
            "y": 1523
          },
          {
            "x": 171,
            "y": 1537
          },
          {
            "x": 131,
            "y": 1537
          }
        ]
      },
      "confidence": 0.9888,
      "id": 149,
      "text": "25,000"
    },
    {
      "boundingBox": {
        "vertices": [
          {
            "x": 191,
            "y": 1524
          },
          {
            "x": 199,
            "y": 1524
          },
          {
            "x": 199,
            "y": 1536
          },
          {
            "x": 191,
            "y": 1536
          }
        ]
      },
      "confidence": 0.9818,
      "id": 150,
      "text": "1"
    },
    {
      "boundingBox": {
        "vertices": [
          {
            "x": 226,
            "y": 1523
          },
          {
            "x": 266,
            "y": 1523
          },
          {
            "x": 266,
            "y": 1537
          },
          {
            "x": 226,
            "y": 1537
          }
        ]
      },
      "confidence": 0.9893,
      "id": 151,
      "text": "25,000"
    },
    {
      "boundingBox": {
        "vertices": [
          {
            "x": 31,
            "y": 1550
          },
          {
            "x": 80,
            "y": 1550
          },
          {
            "x": 80,
            "y": 1566
          },
          {
            "x": 31,
            "y": 1566
          }
        ]
      },
      "confidence": 0.9823,
      "id": 152,
      "text": "판매소계"
    },
    {
      "boundingBox": {
        "vertices": [
          {
            "x": 141,
            "y": 1550
          },
          {
            "x": 170,
            "y": 1550
          },
          {
            "x": 170,
            "y": 1566
          },
          {
            "x": 141,
            "y": 1566
          }
        ]
      },
      "confidence": 0.9876,
      "id": 153,
      "text": "26건"
    },
    {
      "boundingBox": {
        "vertices": [
          {
            "x": 184,
            "y": 1551
          },
          {
            "x": 201,
            "y": 1550
          },
          {
            "x": 201,
            "y": 1565
          },
          {
            "x": 184,
            "y": 1565
          }
        ]
      },
      "confidence": 0.9816,
      "id": 154,
      "text": "27"
    },
    {
      "boundingBox": {
        "vertices": [
          {
            "x": 219,
            "y": 1551
          },
          {
            "x": 265,
            "y": 1551
          },
          {
            "x": 265,
            "y": 1566
          },
          {
            "x": 219,
            "y": 1566
          }
        ]
      },
      "confidence": 0.991,
      "id": 155,
      "text": "517,000"
    },
    {
      "boundingBox": {
        "vertices": [
          {
            "x": 30,
            "y": 1584
          },
          {
            "x": 47,
            "y": 1584
          },
          {
            "x": 48,
            "y": 1601
          },
          {
            "x": 31,
            "y": 1602
          }
        ]
      },
      "confidence": 0.9275,
      "id": 156,
      "text": "전"
    },
    {
      "boundingBox": {
        "vertices": [
          {
            "x": 75,
            "y": 1584
          },
          {
            "x": 97,
            "y": 1584
          },
          {
            "x": 98,
            "y": 1601
          },
          {
            "x": 76,
            "y": 1602
          }
        ]
      },
      "confidence": 0.9662,
      "id": 157,
      "text": "잔:"
    },
    {
      "boundingBox": {
        "vertices": [
          {
            "x": 187,
            "y": 1585
          },
          {
            "x": 245,
            "y": 1585
          },
          {
            "x": 245,
            "y": 1601
          },
          {
            "x": 187,
            "y": 1601
          }
        ]
      },
      "confidence": 0.9843,
      "id": 158,
      "text": "729,600"
    },
    {
      "boundingBox": {
        "vertices": [
          {
            "x": 32,
            "y": 1604
          },
          {
            "x": 98,
            "y": 1604
          },
          {
            "x": 98,
            "y": 1622
          },
          {
            "x": 32,
            "y": 1622
          }
        ]
      },
      "confidence": 0.9717,
      "id": 159,
      "text": "당일합계:"
    },
    {
      "boundingBox": {
        "vertices": [
          {
            "x": 187,
            "y": 1606
          },
          {
            "x": 245,
            "y": 1606
          },
          {
            "x": 245,
            "y": 1623
          },
          {
            "x": 187,
            "y": 1623
          }
        ]
      },
      "confidence": 0.9823,
      "id": 160,
      "text": "517,000"
    },
    {
      "boundingBox": {
        "vertices": [
          {
            "x": 32,
            "y": 1625
          },
          {
            "x": 98,
            "y": 1625
          },
          {
            "x": 98,
            "y": 1643
          },
          {
            "x": 32,
            "y": 1643
          }
        ]
      },
      "confidence": 0.9855,
      "id": 161,
      "text": "할인금액:"
    },
    {
      "boundingBox": {
        "vertices": [
          {
            "x": 196,
            "y": 1627
          },
          {
            "x": 245,
            "y": 1627
          },
          {
            "x": 245,
            "y": 1643
          },
          {
            "x": 196,
            "y": 1643
          }
        ]
      },
      "confidence": 0.9828,
      "id": 162,
      "text": "51,700"
    },
    {
      "boundingBox": {
        "vertices": [
          {
            "x": 30,
            "y": 1647
          },
          {
            "x": 48,
            "y": 1647
          },
          {
            "x": 48,
            "y": 1664
          },
          {
            "x": 31,
            "y": 1665
          }
        ]
      },
      "confidence": 0.9859,
      "id": 163,
      "text": "당"
    },
    {
      "boundingBox": {
        "vertices": [
          {
            "x": 75,
            "y": 1647
          },
          {
            "x": 97,
            "y": 1647
          },
          {
            "x": 98,
            "y": 1664
          },
          {
            "x": 76,
            "y": 1664
          }
        ]
      },
      "confidence": 0.9672,
      "id": 164,
      "text": "잔:"
    },
    {
      "boundingBox": {
        "vertices": [
          {
            "x": 175,
            "y": 1648
          },
          {
            "x": 245,
            "y": 1648
          },
          {
            "x": 245,
            "y": 1665
          },
          {
            "x": 175,
            "y": 1665
          }
        ]
      },
      "confidence": 0.9828,
      "id": 165,
      "text": "1,194,900"
    },
    {
      "boundingBox": {
        "vertices": [
          {
            "x": 32,
            "y": 1684
          },
          {
            "x": 98,
            "y": 1684
          },
          {
            "x": 98,
            "y": 1702
          },
          {
            "x": 32,
            "y": 1702
          }
        ]
      },
      "confidence": 0.9566,
      "id": 166,
      "text": "매입전잔:"
    },
    {
      "boundingBox": {
        "vertices": [
          {
            "x": 236,
            "y": 1688
          },
          {
            "x": 245,
            "y": 1687
          },
          {
            "x": 245,
            "y": 1698
          },
          {
            "x": 236,
            "y": 1698
          }
        ]
      },
      "confidence": 0.9747,
      "id": 167,
      "text": "0"
    },
    {
      "boundingBox": {
        "vertices": [
          {
            "x": 32,
            "y": 1703
          },
          {
            "x": 98,
            "y": 1703
          },
          {
            "x": 98,
            "y": 1723
          },
          {
            "x": 32,
            "y": 1723
          }
        ]
      },
      "confidence": 0.9711,
      "id": 168,
      "text": "매입잔액:"
    },
    {
      "boundingBox": {
        "vertices": [
          {
            "x": 11,
            "y": 1742
          },
          {
            "x": 25,
            "y": 1741
          },
          {
            "x": 25,
            "y": 1755
          },
          {
            "x": 11,
            "y": 1755
          }
        ]
      },
      "confidence": 0.9145,
      "id": 169,
      "text": "※"
    },
    {
      "boundingBox": {
        "vertices": [
          {
            "x": 25,
            "y": 1742
          },
          {
            "x": 47,
            "y": 1742
          },
          {
            "x": 47,
            "y": 1756
          },
          {
            "x": 25,
            "y": 1756
          }
        ]
      },
      "confidence": 0.9969,
      "id": 170,
      "text": "1차"
    },
    {
      "boundingBox": {
        "vertices": [
          {
            "x": 11,
            "y": 1757
          },
          {
            "x": 25,
            "y": 1758
          },
          {
            "x": 25,
            "y": 1772
          },
          {
            "x": 11,
            "y": 1772
          }
        ]
      },
      "confidence": 0.9835,
      "id": 171,
      "text": "※"
    },
    {
      "boundingBox": {
        "vertices": [
          {
            "x": 25,
            "y": 1758
          },
          {
            "x": 64,
            "y": 1758
          },
          {
            "x": 64,
            "y": 1773
          },
          {
            "x": 25,
            "y": 1773
          }
        ]
      },
      "confidence": 0.9876,
      "id": 172,
      "text": "표시는"
    },
    {
      "boundingBox": {
        "vertices": [
          {
            "x": 66,
            "y": 1757
          },
          {
            "x": 154,
            "y": 1757
          },
          {
            "x": 154,
            "y": 1773
          },
          {
            "x": 66,
            "y": 1773
          }
        ]
      },
      "confidence": 0.985,
      "id": 173,
      "text": "미송상품입니다."
    },
    {
      "boundingBox": {
        "vertices": [
          {
            "x": 133,
            "y": 1779
          },
          {
            "x": 165,
            "y": 1779
          },
          {
            "x": 165,
            "y": 1787
          },
          {
            "x": 133,
            "y": 1787
          }
        ]
      },
      "confidence": 0.9919,
      "id": 174,
      "text": "===="
    },
    {
      "boundingBox": {
        "vertices": [
          {
            "x": 11,
            "y": 1790
          },
          {
            "x": 252,
            "y": 1791
          },
          {
            "x": 252,
            "y": 1808
          },
          {
            "x": 11,
            "y": 1806
          }
        ]
      },
      "confidence": 0.9224,
      "id": 175,
      "text": "*입금처:국민은행016702-04-566291(김누리)"
    },
    {
      "boundingBox": {
        "vertices": [
          {
            "x": 11,
            "y": 1808
          },
          {
            "x": 79,
            "y": 1808
          },
          {
            "x": 79,
            "y": 1823
          },
          {
            "x": 11,
            "y": 1823
          }
        ]
      },
      "confidence": 0.9934,
      "id": 176,
      "text": "*상기금액은"
    },
    {
      "boundingBox": {
        "vertices": [
          {
            "x": 80,
            "y": 1808
          },
          {
            "x": 143,
            "y": 1808
          },
          {
            "x": 143,
            "y": 1823
          },
          {
            "x": 80,
            "y": 1823
          }
        ]
      },
      "confidence": 0.9904,
      "id": 177,
      "text": "부가세별도"
    },
    {
      "boundingBox": {
        "vertices": [
          {
            "x": 145,
            "y": 1808
          },
          {
            "x": 210,
            "y": 1808
          },
          {
            "x": 210,
            "y": 1823
          },
          {
            "x": 145,
            "y": 1823
          }
        ]
      },
      "confidence": 0.9894,
      "id": 178,
      "text": "금액입니다."
    },
    {
      "boundingBox": {
        "vertices": [
          {
            "x": 11,
            "y": 1824
          },
          {
            "x": 55,
            "y": 1824
          },
          {
            "x": 55,
            "y": 1840
          },
          {
            "x": 11,
            "y": 1840
          }
        ]
      },
      "confidence": 0.9918,
      "id": 179,
      "text": "*샘플은"
    },
    {
      "boundingBox": {
        "vertices": [
          {
            "x": 56,
            "y": 1824
          },
          {
            "x": 114,
            "y": 1824
          },
          {
            "x": 114,
            "y": 1840
          },
          {
            "x": 56,
            "y": 1840
          }
        ]
      },
      "confidence": 0.9887,
      "id": 180,
      "text": "2주이내에"
    },
    {
      "boundingBox": {
        "vertices": [
          {
            "x": 116,
            "y": 1823
          },
          {
            "x": 166,
            "y": 1824
          },
          {
            "x": 165,
            "y": 1840
          },
          {
            "x": 116,
            "y": 1839
          }
        ]
      },
      "confidence": 0.9893,
      "id": 181,
      "text": "미반납시"
    },
    {
      "boundingBox": {
        "vertices": [
          {
            "x": 168,
            "y": 1824
          },
          {
            "x": 257,
            "y": 1824
          },
          {
            "x": 257,
            "y": 1840
          },
          {
            "x": 168,
            "y": 1840
          }
        ]
      },
      "confidence": 0.9886,
      "id": 182,
      "text": "청구처리됩니다."
    },
    {
      "boundingBox": {
        "vertices": [
          {
            "x": 11,
            "y": 1840
          },
          {
            "x": 74,
            "y": 1841
          },
          {
            "x": 74,
            "y": 1857
          },
          {
            "x": 11,
            "y": 1856
          }
        ]
      },
      "confidence": 0.9623,
      "id": 183,
      "text": "*아이보리,"
    },
    {
      "boundingBox": {
        "vertices": [
          {
            "x": 75,
            "y": 1841
          },
          {
            "x": 101,
            "y": 1841
          },
          {
            "x": 101,
            "y": 1856
          },
          {
            "x": 75,
            "y": 1856
          }
        ]
      },
      "confidence": 0.9859,
      "id": 184,
      "text": "백색"
    },
    {
      "boundingBox": {
        "vertices": [
          {
            "x": 104,
            "y": 1841
          },
          {
            "x": 130,
            "y": 1841
          },
          {
            "x": 130,
            "y": 1857
          },
          {
            "x": 104,
            "y": 1857
          }
        ]
      },
      "confidence": 0.9844,
      "id": 185,
      "text": "교환"
    },
    {
      "boundingBox": {
        "vertices": [
          {
            "x": 132,
            "y": 1841
          },
          {
            "x": 158,
            "y": 1841
          },
          {
            "x": 158,
            "y": 1857
          },
          {
            "x": 132,
            "y": 1857
          }
        ]
      },
      "confidence": 0.9836,
      "id": 186,
      "text": "반품"
    },
    {
      "boundingBox": {
        "vertices": [
          {
            "x": 160,
            "y": 1841
          },
          {
            "x": 184,
            "y": 1841
          },
          {
            "x": 184,
            "y": 1857
          },
          {
            "x": 160,
            "y": 1857
          }
        ]
      },
      "confidence": 0.9887,
      "id": 187,
      "text": "되지"
    },
    {
      "boundingBox": {
        "vertices": [
          {
            "x": 187,
            "y": 1841
          },
          {
            "x": 242,
            "y": 1841
          },
          {
            "x": 242,
            "y": 1857
          },
          {
            "x": 187,
            "y": 1857
          }
        ]
      },
      "confidence": 0.9884,
      "id": 188,
      "text": "않습니다."
    },
    {
      "boundingBox": {
        "vertices": [
          {
            "x": 11,
            "y": 1858
          },
          {
            "x": 79,
            "y": 1858
          },
          {
            "x": 79,
            "y": 1874
          },
          {
            "x": 11,
            "y": 1874
          }
        ]
      },
      "confidence": 0.9943,
      "id": 189,
      "text": "*세금계산서"
    },
    {
      "boundingBox": {
        "vertices": [
          {
            "x": 81,
            "y": 1858
          },
          {
            "x": 107,
            "y": 1858
          },
          {
            "x": 107,
            "y": 1873
          },
          {
            "x": 81,
            "y": 1873
          }
        ]
      },
      "confidence": 0.9806,
      "id": 190,
      "text": "매월"
    },
    {
      "boundingBox": {
        "vertices": [
          {
            "x": 108,
            "y": 1858
          },
          {
            "x": 159,
            "y": 1858
          },
          {
            "x": 159,
            "y": 1874
          },
          {
            "x": 108,
            "y": 1874
          }
        ]
      },
      "confidence": 0.9924,
      "id": 191,
      "text": "10일까지"
    },
    {
      "boundingBox": {
        "vertices": [
          {
            "x": 162,
            "y": 1858
          },
          {
            "x": 227,
            "y": 1858
          },
          {
            "x": 227,
            "y": 1873
          },
          {
            "x": 162,
            "y": 1873
          }
        ]
      },
      "confidence": 0.987,
      "id": 192,
      "text": "발행됩니다."
    },
    {
      "boundingBox": {
        "vertices": [
          {
            "x": 90,
            "y": 1927
          },
          {
            "x": 194,
            "y": 1927
          },
          {
            "x": 194,
            "y": 1942
          },
          {
            "x": 90,
            "y": 1942
          }
        ]
      },
      "confidence": 0.9908,
      "id": 193,
      "text": "23216486313339"
    }
  ],
  "metadata": {
    "pages": [
      {
        "height": 1950,
        "width": 283,
        "page": 1
      }
    ]
  }
}